{
  "n": 79,
  "name": "20 Second Game Jam 2025",
  "url": "https://itch.io/jam/20-second-game-jam-2025",
  "theme": "Lasts only 20 seconds, Squash/Stretch, Shadow/Light, Pick it/Lick it/Roll it/Flick it",
  "slug": "20-second-game-jam-2025",
  "jamMeta": {
    "jamType": "ongoing",
    "joined": "",
    "entries": "623",
    "title": "20 Second Game Jam 2025",
    "jamURL": "https://itch.io/jam/20-second-game-jam-2025",
    "hosts": {
      "Akzidenz": "https://akzidenz.itch.io",
      "marc": "https://fascinationworks.itch.io",
      "xenobrain": "https://xenobrain.itch.io",
      "#20SecondGameJam": "https://bsky.app/hashtag/20SecondGameJam"
    },
    "jamID": "409466"
  },
  "totalEntries": 537,
  "ranked": true,
  "hasCategories": false,
  "needsManualSelection": false,
  "categories": [],
  "topGames": [
    {
      "gameId": 3663954,
      "gameUrl": "https://gabemcarvalho.itch.io/dont-stare",
      "overallRank": 1,
      "topCategories": [],
      "resultData": null,
      "entryData": {
        "rating_count": 0,
        "url": "/jam/20-second-game-jam-2025/rate/3663954",
        "game": {
          "cover": "https://img.itch.zone/aW1nLzI0NDY0NzE2LnBuZw==/300x240%23c/aEOv5n.png",
          "cover_color": "#190B11",
          "url": "https://gabemcarvalho.itch.io/dont-stare",
          "id": 3663954,
          "short_text": "How many rejections can you rack up before getting kicked out?",
          "title": "Don't Stare",
          "user": {
            "id": 6885377,
            "url": "https://gabemcarvalho.itch.io",
            "name": "gabemcarvalho"
          },
          "platforms": [
            "windows",
            "web"
          ]
        },
        "created_at": "2025-12-11 02:35:15",
        "id": 806897,
        "contributors": [
          {
            "url": "https://gabemcarvalho.itch.io",
            "name": "gabemcarvalho"
          },
          {
            "url": "https://owengideon.itch.io",
            "name": "Owen Gideon"
          }
        ],
        "coolness": 0
      },
      "details": {
        "title": "Don't Stare",
        "description": "\nFollow us to see what's next: Bluesky\nHover and hold your cursor over your date's weak spot. Stare long enough, and they will get uncomfortable and flee. \nNo need to click during the Speed Dating, a gaze does more than action. See how many rejections you can rack up in 20 seconds.\nPay attention to anomalies in the mix. What makes them self-conscious may not be what you first think.\nCreated By\nGabe M Carvalho - Code, Sound, VFX\nOwen Melisek - Art, Music\nAn Ozone Soft Production\n\nMore coming soon... 👁️👁️🚫",
        "screenshots": [
          "https://img.itch.zone/aW1hZ2UvMzY2Mzk1NC8yNDQ5NjkwNS5qcGc=/original/rXbfiZ.jpg",
          "https://img.itch.zone/aW1hZ2UvMzY2Mzk1NC8yNDQ5Njk2MS5qcGc=/original/ssiNio.jpg",
          "https://img.itch.zone/aW1hZ2UvMzY2Mzk1NC8yNDQ5NjkwNi5qcGc=/original/gP38FH.jpg",
          "https://img.itch.zone/aW1hZ2UvMzY2Mzk1NC8yNDQ5NjkzOC5qcGc=/original/9trPjG.jpg",
          "https://img.itch.zone/aW1hZ2UvMzY2Mzk1NC8yNDQ5NjkxNC5qcGc=/original/Xt3dMb.jpg"
        ],
        "moreInfo": {
          "Updated": "16 days ago",
          "Status": "Released",
          "Platforms": "HTML5, Windows",
          "Rating": "Rated 4.6 out of 5 stars(452 total ratings)",
          "Authors": "gabemcarvalho, Owen Gideon",
          "Genre": "Interactive Fiction",
          "Made with": "GameMaker, Adobe Photoshop",
          "Tags": "anomaly, Atmospheric, Creepy, Dating Sim, Horror, Pixel Art, Psychological Horror",
          "Average session": "A few minutes",
          "Languages": "English",
          "Inputs": "Mouse, Touchscreen, Stylus"
        }
      }
    },
    {
      "gameId": 4120158,
      "gameUrl": "https://emankcin01.itch.io/xmas-kpi",
      "overallRank": 2,
      "topCategories": [],
      "resultData": null,
      "entryData": {
        "rating_count": 0,
        "url": "/jam/20-second-game-jam-2025/rate/4120158",
        "game": {
          "cover": "https://img.itch.zone/aW1nLzI0NjQwNTY3LnBuZw==/300x240%23c/5lSSFy.png",
          "cover_color": "#1B3858",
          "url": "https://emankcin01.itch.io/xmas-kpi",
          "id": 4120158,
          "short_text": "Ho, ho, ho... Do you like the gift, kiddo?",
          "title": "Xmas KPI | 圣诞KPI",
          "user": {
            "id": 8627829,
            "url": "https://emankcin01.itch.io",
            "name": "Emankcin01"
          },
          "platforms": [
            "web"
          ]
        },
        "created_at": "2025-12-16 01:03:42",
        "id": 808934,
        "coolness": 0
      },
      "details": {
        "title": "Xmas KPI | 圣诞KPI",
        "description": "English [Click Here]\n简体中文 [点此查看]\n\n- - - [English] - - -\n\n\n\nHo, ho, ho... Do you like the gift, kiddo?\n\nMade for 20 Second Game Jam 2025\nExtra Short: 20-Sec Gameplay\nMultiple Endings: 21 Endings In Total\nMeaningful Choices: Your Choices Define The End\nMulti-Language Support: En / ZhS / ZhT\n\nThe initial game load may take a little while. Thanks for your patience.\n💻 SUPPORTED DEVICES\nDEVICESSTATUSKeyboard & Mouse\n✔\nMobile Touchscreen (Phone/Tablet)\n✔\nController\nuntested\n\n🎮 CONTROLS\nACTIONSKEYBOARDMOUSE / TOUCHSCREENMove Cursor[←↑↓→] or [WASD]\nClick / TapConfirm[Space] or [Enter] or [Z]\nClick / TapFast-Forward TextHold [Space] or [Enter] or [Z]Click / Tap and HoldCancel / Close / Back[Tab] or [Esc] or [X]\nClick / TapFullscreen\n[F4]\nOpen Text History[H]\n\n🐞 FOUND A BUG?\nBUG TYPEWHAT TO DOError: Failed to initialize graphics\nThis sometimes occurs in the Edge browser. Please try using a different browser, such as Chrome or Firefox.\nError: Resource loading failure [Retry]\nThis may occur on mobile devices during initial load. Please tap 'Retry' to continue.\nOther Errors or Bugs\nPlease share a comment with a screenshot! Any extra details below would be extremely helpful:  \n 1. How the bug was triggered (Steps to reproduce)  \n 2. Your device (e.g., Desktop / Laptop / Phone / Tablet)  \n 3. Your operating system (e.g., Windows / Mac / Linux / iOS / Android)  \n 4. Browser used (e.g., Chrome / Firefox / Edge)  \n This information will significantly speed up the fix. Thank you for your help! \n🎥 FOR STREAMERS \nStreaming is welcomed! Feel free to show your genuine reactions and feelings. All insights (including the positive, the negative, and the bugs) are highly valuable and appreciated. If you're interested in voice acting for the characters during the stream, you can turn down or turn off the \"VO Volume\" in the Options menu.\n\nGet the exclusive 4K Wallpapers!\nLike this game? Grab the DLC and decorate your devices with exclusive Xmas KPI-themed Wallpapers!\n★ Wallpaper Bundle ★\nPrice: $2.00 USD\nContent: five 4K Wallpapers (3840 x 2160 pixels)\nLicense: Non-Commercial Personal Use\n\n\n\n\nSolo Developed By：Emankcin\nWebsite | Steam | Itch | Bilibili | Mihuashi | Youtube\nMORE GAMES\n✨Liked this game? Check out my other games!✨\n\n\n\n\n\n\n\n\n\n\n\n\n- - - [简体中文 (Simplified Chinese)] - - -\n\n\n\nHo, ho, ho... 喜欢这份礼物吗，小朋友？\n\nGame Jam 20 Second Game Jam 2025 期间基于主题「20秒」制作\n超短篇：20 秒玩法\n\n多结局：共计 21 种结局\n\n有意义的选择：你的选择决定结局\n\n多语言支持：支持英文 / 简中 / 繁中\n\n游戏首次加载可能需要一些时间，感谢您的耐心等待\n💻 支持设备\n设备状态键盘 + 鼠标\n✔\n移动端触摸屏（手机/平板）\n✔\n手柄\n未测试\n\n🎮 按键说明\n动作键盘鼠标 / 触摸屏移动光标[←↑↓→] 或 [WASD]\n点击确认[空格键] 或 [回车键] 或 [Z] \n点击\n快进文本按住 [空格键] 或 [回车键] 或 [Z] 点击并按住取消/关闭/返回[Tab] 或 [Esc] 或 [X]\n点击\n全屏[F4]\n\n打开文本历史[H]\n\n\n🐞 发现BUG？\nBUG类型处理方法Error: Failed to initialize graphics\n此报错有时会在Edge浏览器中出现。请尝试使用其他浏览器，如Chrome或Firefox。\nError: Resource loading failure [Retry]\n此报错可能在移动设备初次加载时出现。请点击“Retry”继续。\n其他错误或BUG\n请附带截图发表评论！以下额外信息将非常有帮助：\n 1. BUG是如何触发的（重现步骤）\n 2. 您的设备（例：台式机 / 笔记本 / 手机 / 平板）\n 3. 您的操作系统（例：Windows / Mac / Linux / iOS / Android）\n 4. 使用的浏览器（例：Chrome / Firefox / Edge）\n 这些信息将十分有助于加快修复速度。感谢您的帮助！\n\n🎥 关于直播\n欢迎直播！请自由地展示您的真实反应和感受。所有见解（包括正面的、负面的，以及BUG）都极具价值，非常感谢！如果您有兴趣在直播时为角色配音，可以在“选项”菜单中调低或关闭 VO 音量。\n\n获得独家 4K 壁纸！\n喜欢这款游戏吗？入手DLC，用 Xmas-KPI 独家主题壁纸装扮您的设备吧！\n★ 壁纸捆绑包 ★\n价格： $2.00 USD\n内容： 五张 4K 壁纸（3840 x 2160 像素）\n许可：非商业个人使用\n\n\n\n\n独立开发：Emankcin\n\n个人网站 | 哔哩哔哩 | 米画师 | Steam | Itch | Youtube\n更多游戏\n✨喜欢这个游戏吗？看看我的其它游戏吧！✨\n\n\n\n\n\n\n\n\n\n\n",
        "screenshots": [
          "https://img.itch.zone/aW1hZ2UvNDEyMDE1OC8yNDY4OTU0MC5wbmc=/original/alacTD.png",
          "https://img.itch.zone/aW1hZ2UvNDEyMDE1OC8yNDY4OTUwNS5wbmc=/original/dvBYXh.png",
          "https://img.itch.zone/aW1hZ2UvNDEyMDE1OC8yNDY4OTUwNi5wbmc=/original/6mLlnH.png",
          "https://img.itch.zone/aW1hZ2UvNDEyMDE1OC8yNDY0MDU1My5wbmc=/original/QOTfGw.png",
          "https://img.itch.zone/aW1hZ2UvNDEyMDE1OC8yNDY0MDg1NC5wbmc=/original/M0Z%2Bdt.png"
        ],
        "moreInfo": {
          "Status": "Released",
          "Platforms": "HTML5",
          "Rating": "Rated 4.7 out of 5 stars(15 total ratings)",
          "Author": "Emankcin01",
          "Genre": "Interactive Fiction, Visual Novel",
          "Made with": "RPG Maker",
          "Tags": "Anime, Christmas, Creepy, Meaningful Choices, Multiple Endings, RPG Maker, Short, Story Rich",
          "Average session": "A few seconds",
          "Languages": "English, Chinese, Chinese (Simplified), Chinese (Traditional)",
          "Inputs": "Keyboard, Mouse, Touchscreen, Smartphone"
        }
      }
    },
    {
      "gameId": 4117311,
      "gameUrl": "https://mindream.itch.io/the-unknown",
      "overallRank": 3,
      "topCategories": [],
      "resultData": null,
      "entryData": {
        "rating_count": 0,
        "url": "/jam/20-second-game-jam-2025/rate/4117311",
        "game": {
          "cover": "https://img.itch.zone/aW1nLzI0NTM2MTkyLnBuZw==/300x240%23c/4D4Y1g.png",
          "cover_color": "#000000",
          "url": "https://mindream.itch.io/the-unknown",
          "id": 4117311,
          "short_text": "A short narrative game with multiple endings about taking a step towards the unknown you can't see.",
          "title": "The Unknown",
          "user": {
            "id": 15354147,
            "url": "https://mindream.itch.io",
            "name": "Mindream"
          },
          "platforms": [
            "web"
          ]
        },
        "created_at": "2025-12-13 19:06:02",
        "id": 807737,
        "coolness": 0
      },
      "details": {
        "title": "The Unknown",
        "description": "The Unknown is a very short narrative game about taking a step towards the unknown you can't see. \nThis game was created for the 20 Second Game Jam 2025 and has 3 endings for you to find.Full screen recommended for better immersion (click on the blue button on the bottom right of the window)\nThank you for playing and any constructive feedback is welcome !\n---\nControls : (the camera is fixed on purpose)\nW/Z/Up Arrow : Move forward\n\nS/Down Arrow  : Move backwards\n\n",
        "screenshots": [
          "https://img.itch.zone/aW1hZ2UvNDExNzMxMS8yNDUzNTYxMy5wbmc=/original/eokFYP.png",
          "https://img.itch.zone/aW1hZ2UvNDExNzMxMS8yNDU1NzQ1OS5wbmc=/original/bQ3wG8.png"
        ],
        "moreInfo": {
          "Updated": "29 days ago",
          "Status": "Prototype",
          "Platforms": "HTML5",
          "Rating": "Rated 4.8 out of 5 stars(8 total ratings)",
          "Author": "Mindream",
          "Genre": "Adventure",
          "Tags": "3D, Atmospheric, Experimental, First-Person, No AI, Short, Unreal Engine"
        }
      }
    },
    {
      "gameId": 4118574,
      "gameUrl": "https://robinfield.itch.io/newcmr",
      "overallRank": 4,
      "topCategories": [],
      "resultData": null,
      "entryData": {
        "rating_count": 0,
        "url": "/jam/20-second-game-jam-2025/rate/4118574",
        "game": {
          "cover": "https://img.itch.zone/aW1nLzI0ODg2NDc4LnBuZw==/300x240%23c/hmkTzm.png",
          "cover_color": "#141414",
          "url": "https://robinfield.itch.io/newcmr",
          "id": 4118574,
          "short_text": "Microaggressive.",
          "title": "Newcmr",
          "user": {
            "id": 228290,
            "url": "https://robinfield.itch.io",
            "name": "Robin Field"
          },
          "platforms": [
            "windows",
            "web"
          ]
        },
        "created_at": "2025-12-15 19:55:14",
        "id": 808782,
        "coolness": 0
      },
      "details": {
        "title": "Newcmr",
        "description": "Frantically hunt down Mr 'Goldman' Mickey before his vile plan can be put into motion; blasting unrelenting streams of his gangsters as you crawl forward.Newcmr is a violent high-speed shooter with an in-depth reloading mechanic & frantic, bloody shootouts. If you want to make your way to the secret levels, you'll have to truly master your weapon.\nOriginally made for 20 Second Game Jam by Robin Field.\nDefault keyboard controls:\n(Rebindable in settings)\nMove LeftLeft ArrowMove RightRight ArrowLook UpUp ArrowLook Down / CrouchDown ArrowJumpZShoot / PunchXReloadC\n\nIf you like this game & are the generous type, I can now be supported here:\nhttps://ko-fi.com/hobfield\nThanks for playing!",
        "screenshots": [
          "https://img.itch.zone/aW1hZ2UvNDExODU3NC8yNDU3NDU3OS5wbmc=/original/cCuZOh.png",
          "https://img.itch.zone/aW1hZ2UvNDExODU3NC8yNDU3NDU3Ny5wbmc=/original/jnuL7t.png",
          "https://img.itch.zone/aW1hZ2UvNDExODU3NC8yNDU3NDU3OC5wbmc=/original/R0ZBXw.png",
          "https://img.itch.zone/aW1hZ2UvNDExODU3NC8yNDU3NDU4MC5wbmc=/original/DQX7Wl.png"
        ],
        "moreInfo": {
          "Status": "Released",
          "Platforms": "HTML5, Windows",
          "Rating": "Rated 4.6 out of 5 stars(24 total ratings)",
          "Author": "Robin Field",
          "Genre": "Action, Platformer, Shooter",
          "Made with": "GameMaker, FL Studio, Paint.net",
          "Tags": "2D, Atmospheric, Creepy, Fast-Paced, No AI, Pixel Art, Short, Violent",
          "Average session": "A few seconds",
          "Languages": "English",
          "Inputs": "Keyboard, Xbox controller",
          "Accessibility": "Subtitles, Configurable controls, High-contrast"
        }
      }
    },
    {
      "gameId": 4108783,
      "gameUrl": "https://amptomp.itch.io/how-to-walk-out-the-door",
      "overallRank": 5,
      "topCategories": [],
      "resultData": null,
      "entryData": {
        "rating_count": 0,
        "url": "/jam/20-second-game-jam-2025/rate/4108783",
        "game": {
          "cover": "https://img.itch.zone/aW1nLzI0NTg5MzkzLnBuZw==/300x240%23c/%2B9Uv3S.png",
          "cover_color": "#000000",
          "url": "https://amptomp.itch.io/how-to-walk-out-the-door",
          "id": 4108783,
          "short_text": "20 second game about walking out the door",
          "title": "how to walk out the door",
          "user": {
            "id": 6936427,
            "url": "https://amptomp.itch.io",
            "name": "amptomp"
          },
          "platforms": [
            "windows",
            "web"
          ]
        },
        "created_at": "2025-12-16 04:47:02",
        "id": 809098,
        "coolness": 0
      },
      "details": {
        "title": "how to walk out the door",
        "description": "instructions: walk out the door\n\ncreated for 20 second game jam 2025\nfeaturing anton pätsi & lucy woodallfilmed by benjamin pilbrowdesigned by anton\nthank you henri, victoria, celina, flan, show&tell ppl for feedback :)",
        "screenshots": [
          "https://img.itch.zone/aW1hZ2UvNDEwODc4My8yNDU3Nzc5Ni5qcGc=/original/GZ%2Fsoo.jpg",
          "https://img.itch.zone/aW1hZ2UvNDEwODc4My8yNDU3Nzc5Ny5qcGc=/original/NGXTbz.jpg",
          "https://img.itch.zone/aW1hZ2UvNDEwODc4My8yNDU3Nzc5NC5qcGc=/original/EHjnw4.jpg",
          "https://img.itch.zone/aW1hZ2UvNDEwODc4My8yNDU3Nzc5My5qcGc=/original/Pjw2JV.jpg",
          "https://img.itch.zone/aW1hZ2UvNDEwODc4My8yNDU3Nzc5NS5qcGc=/original/dSgtUV.jpg"
        ],
        "moreInfo": {
          "Status": "Released",
          "Platforms": "HTML5, Windows",
          "Rating": "Rated 4.9 out of 5 stars(128 total ratings)",
          "Author": "amptomp",
          "Genre": "Interactive Fiction",
          "Made with": "Godot",
          "Tags": "Experimental, Fast-Paced, Indie, Narrative, Short, Singleplayer, Slice Of Life, Story Rich, Typing",
          "Average session": "A few seconds",
          "Languages": "English",
          "Inputs": "Keyboard"
        }
      }
    },
    {
      "gameId": 4071829,
      "gameUrl": "https://allalonegamez.itch.io/a-20-second-metroidvania",
      "overallRank": 6,
      "topCategories": [],
      "resultData": null,
      "entryData": {
        "rating_count": 0,
        "url": "/jam/20-second-game-jam-2025/rate/4071829",
        "game": {
          "cover": "https://img.itch.zone/aW1nLzI0MzAyMjUxLnBuZw==/300x240%23c/dzuqM5.png",
          "cover_color": "#000000",
          "url": "https://allalonegamez.itch.io/a-20-second-metroidvania",
          "id": 4071829,
          "short_text": "A metroidvania for speedrunners",
          "title": "A 20 Second Metroidvania",
          "user": {
            "id": 4728930,
            "url": "https://allalonegamez.itch.io",
            "name": "allalonegamez"
          },
          "platforms": [
            "web"
          ]
        },
        "created_at": "2025-11-29 05:07:38",
        "id": 801586,
        "coolness": 0
      },
      "details": {
        "title": "A 20 Second Metroidvania",
        "description": "IMPORTANT : After clicking on the \"run game\" button, click again in the same spot when the image appears.\nA 5-minute Metroidvania (or 20 seconds if you know all the secrets).\nYou can try my full-length Metroidvania here: Link\nActionKeyboardGame BoyMove\nArrow Keys or WASD\nD-Pad\nJump\nAlt, Z or J\nA\nRestart the level\nEnter (Return)\nStart\nStop the timer\nShift\nSelect\n\nCredits :\nFollow me on BlueSky  : https://bsky.app/profile/allalonegamez.bsky.social\n\nMaking the game (concept, level design, art...) : allalonegamez\n----------------------------------------------------------------------------------------------------------Copyright and Distribution Disclaimer :\nAll rights to this game are retained by the author. \nNo rights are granted to host, upload, distribute, reproduce, archive, or make the work publicly available, in part or in full, without the author’s prior explicit written permission. \nThe author’s participation in competitions, showcases, public events, or exhibitions does not imply any transfer, licensing, or waiver of copyright or distribution rights. \nAny unauthorized hosting or publication of this work is strictly prohibited.",
        "screenshots": [
          "https://img.itch.zone/aW1hZ2UvNDA3MTgyOS8yNDI5OTI0OS5wbmc=/original/Y%2FvFas.png",
          "https://img.itch.zone/aW1hZ2UvNDA3MTgyOS8yNDI5OTI1MS5wbmc=/original/JUVPuk.png",
          "https://img.itch.zone/aW1hZ2UvNDA3MTgyOS8yNDI5OTMyOC5wbmc=/original/YhXENt.png",
          "https://img.itch.zone/aW1hZ2UvNDA3MTgyOS8yNDI5OTI1MC5wbmc=/original/2DzmKO.png"
        ],
        "moreInfo": {
          "Status": "Released",
          "Platforms": "HTML5",
          "Rating": "Rated 4.4 out of 5 stars(12 total ratings)",
          "Author": "allalonegamez",
          "Genre": "Platformer",
          "Made with": "GB Studio",
          "Tags": "analogue-pocket, game-boy, Game Boy, Game Boy ROM, gbstudio, mario, Metroidvania, Short, Speedrun, Time Attack"
        }
      }
    },
    {
      "gameId": 4102660,
      "gameUrl": "https://biscuitlocker.itch.io/gb-ninja-booger",
      "overallRank": 7,
      "topCategories": [],
      "resultData": null,
      "entryData": {
        "rating_count": 0,
        "url": "/jam/20-second-game-jam-2025/rate/4102660",
        "game": {
          "cover": "https://img.itch.zone/aW1nLzI0NDUyMjAxLnBuZw==/300x240%23c/wts1VM.png",
          "cover_color": "#000000",
          "url": "https://biscuitlocker.itch.io/gb-ninja-booger",
          "id": 4102660,
          "short_text": "20 Second Game Jam - Gameboy ninja shooting gallery with boogers",
          "title": "GB Ninja Booger!",
          "user": {
            "id": 173559,
            "url": "https://biscuitlocker.itch.io",
            "name": "biscuitlocker"
          },
          "platforms": [
            "web"
          ]
        },
        "created_at": "2025-12-08 12:05:46",
        "id": 805992,
        "coolness": 0
      },
      "details": {
        "title": "GB Ninja Booger!",
        "description": "An entry to the 20 Second Game Jam 2025.Theme chosen: \"Pick it/Lick it/Roll it/Flick it\"\nInstructions \nYou have 20 seconds to shoot as many ninjas as possible.Don't let ninjas get too close or it's game over!Don't miss for multiplier score bonuses.Avoid being hit for bonus life points at the end. Hold the shoot button for a mega booger shot!\nControls\nD-Pad / Cursors - Move & Select DifficultyA Button / Z - Shoot BoogerStart Button / Enter - Start & Pause Game\n    Select Button / Shift - Music On & Off\nAbout\nThe .gbc file can be played on an original Gameboy Color and emulators.\n    \nMade by BiscuitLocker, using GBStudio 4 and Aseprite.\n    \n    \nMusic: \"Hypergolic Blast Off\" by Yogi/Tronimal\n    \n\n\n",
        "screenshots": [
          "https://img.itch.zone/aW1hZ2UvNDEwMjY2MC8yNDQ1MTc3OC5wbmc=/original/ssMDdI.png",
          "https://img.itch.zone/aW1hZ2UvNDEwMjY2MC8yNDQ1MTc3Ni5wbmc=/original/rctMT0.png",
          "https://img.itch.zone/aW1hZ2UvNDEwMjY2MC8yNDQ1MTc3NS5wbmc=/original/5RnUd6.png",
          "https://img.itch.zone/aW1hZ2UvNDEwMjY2MC8yNDQ1MTc3Ny5wbmc=/original/jlbF1G.png",
          "https://img.itch.zone/aW1hZ2UvNDEwMjY2MC8yNjAzNjY1Ny5wbmc=/original/djl%2F%2Ft.png"
        ],
        "moreInfo": {
          "Updated": "1 day ago",
          "Status": "Prototype",
          "Platforms": "HTML5",
          "Rating": "Rated 5.0 out of 5 stars(4 total ratings)",
          "Author": "biscuitlocker",
          "Genre": "Shooter",
          "Tags": "Game Boy, Ninja, Pixel Art"
        }
      }
    },
    {
      "gameId": 3987200,
      "gameUrl": "https://donythepony.itch.io/sexy-cyber-kiosk",
      "overallRank": 8,
      "topCategories": [],
      "resultData": null,
      "entryData": {
        "rating_count": 0,
        "url": "/jam/20-second-game-jam-2025/rate/3987200",
        "game": {
          "cover": "https://img.itch.zone/aW1nLzI0NTU2NjI2LnBuZw==/300x240%23c/jg2V5s.png",
          "cover_color": "#71d0fd",
          "url": "https://donythepony.itch.io/sexy-cyber-kiosk",
          "id": 3987200,
          "short_text": "Take on the perspective of a robo-clerk to serve as many customers as possible in the shortest amount of time!",
          "title": "Sexy Cyber Kiosk",
          "user": {
            "id": 336087,
            "url": "https://donythepony.itch.io",
            "name": "DonyThePony"
          },
          "platforms": [
            "web"
          ]
        },
        "created_at": "2025-12-15 20:32:01",
        "id": 808798,
        "contributors": [
          {
            "url": "https://donythepony.itch.io",
            "name": "DonyThePony"
          },
          {
            "url": "https://graphite-surgeon.itch.io",
            "name": "DaiZa"
          }
        ],
        "coolness": 0
      },
      "details": {
        "title": "Sexy Cyber Kiosk",
        "description": "CONTROLS\n SPACEARROW KEYSCTRL\nENTER to next screen\nINFO:\nIt could happen that the the first load and run lags due to some shaders on the webbuild. Reloading the page solves the issue. ---------------------------------------------------------\nStudies show that increasing flirtiness at the point of sale leads to better sales figures.\nTake on the perspective of a robo-clerk to serve as many customers as possible in the shortest amount of time!\nCAUTION: The new robo-clerks are experimental and can fatally misinterpret requests.\nHow to play: \nUse the arrow keys to enter orders -> Error-free sprees are rewarded! But be careful: one wrong entry can drastically worsen your customers' shopping experience.\nSpam the space bar when a customer craves a pineapple. \nPay attention to subtle hints to give customers a little flirty extra with their orders.\nCredits to Assets \nhttps://godotshaders.com/shader/toon-water-shader-godot-4-4/\nhttps://github.com/Art-Michel/Flowerwall-CRT-shader-for-Godot\nhttps://www.gamedevmarket.net/asset/casual-app-female-voice-announcer",
        "screenshots": [
          "https://img.itch.zone/aW1hZ2UvMzk4NzIwMC8yNDU0Mjg1MS5qcGc=/original/MLLp8p.jpg",
          "https://img.itch.zone/aW1hZ2UvMzk4NzIwMC8yNDU0Mjg0OS5qcGc=/original/GS3Lw2.jpg",
          "https://img.itch.zone/aW1hZ2UvMzk4NzIwMC8yNDU0Mjg1MC5qcGc=/original/EsIa5V.jpg"
        ],
        "moreInfo": {
          "Status": "Released",
          "Platforms": "HTML5",
          "Rating": "Rated 4.8 out of 5 stars(10 total ratings)",
          "Authors": "DonyThePony, DaiZa",
          "Genre": "Simulation",
          "Made with": "Godot",
          "Tags": "Arcade, Cyberpunk, kiosk, sexy",
          "Average session": "A few seconds",
          "Languages": "English"
        }
      }
    },
    {
      "gameId": 4109403,
      "gameUrl": "https://evengy.itch.io/delivered",
      "overallRank": 9,
      "topCategories": [],
      "resultData": null,
      "entryData": {
        "rating_count": 0,
        "url": "/jam/20-second-game-jam-2025/rate/4109403",
        "game": {
          "cover": "https://img.itch.zone/aW1nLzI0NTcyOTc5LnBuZw==/300x240%23c/sRqNB0.png",
          "cover_color": "#FFE1CE",
          "url": "https://evengy.itch.io/delivered",
          "id": 4109403,
          "short_text": "Kick fragile packages to your customers' doorsteps",
          "title": "Delivered",
          "user": {
            "id": 4199007,
            "url": "https://evengy.itch.io",
            "name": "evengy"
          },
          "platforms": [
            "windows",
            "web"
          ]
        },
        "created_at": "2025-12-12 07:45:34",
        "id": 807330,
        "coolness": 0
      },
      "details": {
        "title": "Delivered",
        "description": "Play as a courier who absolutely hates his job and spends all his money on karate lessons.\nDeliver fragile packages to impatient customers under ridiculous time pressure by kicking them to their destination. Use your poorly controlled anger to send parcels through hallways.\nWishlist on steam\nP.S.\nWASD, shift, space, lmb mouse.\nP.P.S.\nDesktop build is updated more frequently.",
        "screenshots": [
          "https://img.itch.zone/aW1hZ2UvNDEwOTQwMy8yNDU0MjQyNS5wbmc=/original/QkoT%2Fb.png",
          "https://img.itch.zone/aW1hZ2UvNDEwOTQwMy8yNDU0MjQ1My5qcGc=/original/pZOVjI.jpg",
          "https://img.itch.zone/aW1hZ2UvNDEwOTQwMy8yNDU0MjQ1NS5qcGc=/original/uIe5ce.jpg",
          "https://img.itch.zone/aW1hZ2UvNDEwOTQwMy8yNDU0MjQ2MS5qcGc=/original/JQgyAk.jpg",
          "https://img.itch.zone/aW1hZ2UvNDEwOTQwMy8yNDUxNzM2NC5naWY=/original/ZGhrZl.gif"
        ],
        "moreInfo": {
          "Updated": "8 days ago",
          "Status": "Prototype",
          "Platforms": "HTML5, Windows",
          "Rating": "Rated 4.9 out of 5 stars(15 total ratings)",
          "Author": "evengy",
          "Genre": "Action",
          "Made with": "Unity, Blender",
          "Tags": "Comedy, Difficult, Fast-Paced, Funny, No AI, Physics, PSX (PlayStation), rage, Retro, Time Attack",
          "Average session": "A few seconds",
          "Languages": "English",
          "Inputs": "Keyboard, Mouse",
          "Links": "Bluesky, Twitter/X"
        }
      }
    },
    {
      "gameId": 4114856,
      "gameUrl": "https://aniimewolf.itch.io/who-is-ayame",
      "overallRank": 10,
      "topCategories": [],
      "resultData": null,
      "entryData": {
        "rating_count": 0,
        "url": "/jam/20-second-game-jam-2025/rate/4114856",
        "game": {
          "cover": "https://img.itch.zone/aW1nLzI0NTM0NDQ4LnBuZw==/300x240%23c/L2K7lR.png",
          "cover_color": "#eeeeee",
          "url": "https://aniimewolf.itch.io/who-is-ayame",
          "id": 4114856,
          "short_text": "A Persona Influenced by Choices",
          "title": "Who is Ayame?",
          "user": {
            "id": 15299369,
            "url": "https://aniimewolf.itch.io",
            "name": "AniimeWolf"
          },
          "platforms": [
            "web"
          ]
        },
        "created_at": "2025-12-12 16:17:33",
        "id": 807392,
        "coolness": 0
      },
      "details": {
        "title": "Who is Ayame?",
        "description": "Who is Ayame?\nWho is Ayame...?\nWho is....Ayame?\nAyame?\n?\n\nDepending on your decisions, you'll affect Naru's and Ayame's future.\nThe game currently contains 7 endings. You have to find them yourself. \n\nEnding 1 Hint: Something platonic.\nClick to see word. \"Friend\".\n\nEnding 2 Hint: Something not so platonic (feeling).\nClick to see word. \"Love\" or \"Crush\".\n\nEnding 3 Hint: Something NOT platonic.\nClick to see word. \"Wife\" or \"Bride\".\n\nEnding 4 Hint: Something...nurturing?\nClick to see word. \"Mom\" or \"Mother\".\n\nEnding 5 Hint: Something full.\nClick to see word. \"Everything\".\n\nEnding 6 Hint: Something empty.\nClick to see word. \"Nothing\".\n\nEnding 7 Hint (Best Ending): The simplest answer.\nClick to see word. \"Ayame\" or \"You\".\n\n(I might update the game over time to add new endings.)",
        "screenshots": [
          "https://img.itch.zone/aW1hZ2UvNDExNDg1Ni8yNDUzNDQ2Ni5wbmc=/original/5G6ca7.png",
          "https://img.itch.zone/aW1hZ2UvNDExNDg1Ni8yNDUzNDQ2OC5wbmc=/original/gSWRjk.png",
          "https://img.itch.zone/aW1hZ2UvNDExNDg1Ni8yNDUzNDQ3MS5wbmc=/original/op%2BAoL.png",
          "https://img.itch.zone/aW1hZ2UvNDExNDg1Ni8yNDUzNDQ3NC5wbmc=/original/sOMSzk.png"
        ],
        "moreInfo": {
          "Status": "Released",
          "Platforms": "HTML5",
          "Rating": "Rated 5.0 out of 5 stars(7 total ratings)",
          "Author": "AniimeWolf",
          "Genre": "Visual Novel",
          "Made with": "Ren'Py",
          "Tags": "Meaningful Choices, Multiple Endings, Romance, Yandere"
        }
      }
    },
    {
      "gameId": 4066576,
      "gameUrl": "https://wolanboi.itch.io/nyctophobia",
      "overallRank": 11,
      "topCategories": [],
      "resultData": null,
      "entryData": {
        "rating_count": 0,
        "url": "/jam/20-second-game-jam-2025/rate/4066576",
        "game": {
          "cover": "https://img.itch.zone/aW1nLzI0NDkzNjc2LnBuZw==/300x240%23c/zFPAZS.png",
          "cover_color": "#000000",
          "url": "https://wolanboi.itch.io/nyctophobia",
          "id": 4066576,
          "short_text": "Nyctophobia is a horror styled game, made to test your reflexes. Can you survive being constantly chased by the dark?",
          "title": "Nyctophobia",
          "user": {
            "id": 3472741,
            "url": "https://wolanboi.itch.io",
            "name": "Wolan"
          },
          "platforms": [
            "windows",
            "web"
          ]
        },
        "created_at": "2025-12-15 22:50:33",
        "id": 808873,
        "contributors": [
          {
            "url": "https://wolanboi.itch.io",
            "name": "Wolan"
          },
          {
            "url": "https://polskiant.itch.io",
            "name": "Polskiant"
          }
        ],
        "coolness": 0
      },
      "details": {
        "title": "Nyctophobia",
        "description": "Nyctophobia is a horror styled game, made to test your reflexes. Can you survive being constantly chased by the dark?\nWARNING!: The game may stutter on the web build! While it is possible to complete the game in the browser, for the best experience we recommend downloading the executable file, and playing it on your computer. However if you REALLY want to play in the browser, we suggest lowering the 3D scale setting.\nControls:\nA/S/D or Left/Down/Right arrow - Left/Crouch/Right\nIn this game you must battle your fear of the dark in this nonsensical tunnel. Run for your life and reach the elevator, and just maybe, you will survive. Remember:\nDo not let it catch you. Do not let it catch you. Do not let it catch you. Do not let it catch you. Do not let it catch you. Do not let it catch you. Do not let it catch you. Do not let it catch you. Do not let it catch you. Do not let it catch you. Do not let it catch you. Do not let it catch you. Do not let it catch you. Do not let it catch you. Do not let it catch you. Do not let it catch you. Do not let it catch you. Do not let it catch you. Do not let it catch you. Do not let it catch you. Do not let it catch you. Do not let it catch you. Do not let it catch you. Do not let it catch you. Do not let it catch you. Do not let it catch you. Do not let it catch you. Do not let it catch you. Do not let it catch you. Do not let it catch you. Do not let it catch you. Do not let it catch you. Do not let it catch you. Do not let it catch you. Do not let it catch you. Do not let it catch you. Do not let it catch you. Do not let it catch you. Do not let it catch you. Do not let it catch you. Do not let it catch you. Do not let it catch you. Do not let it catch you. Do not let it catch you. Do not let it catch you. Do not let it catch you. Do not let it catch you. Do not let it catch you. Do not let it catch you. Do not let it catch you. Do not let it catch you. Do not let it catch you. Do not let it catch you. Do not let it catch you. Do not let it catch you. Do not let it catch you. Do not let it catch you. Do not let it catch you. Do not let it catch you. Do not let it catch you. Do not let it catch you. Do not let it catch you. Do not let it catch you. Do not let it catch you. Do not let it catch you. Do not let it catch you. Do not let it catch you. Do not let it catch you. Do not let it catch you. Do not let it catch you. Do not let it catch you. Do not let it catch you. Do not let it catch you. Do not let it catch you. Do not let it catch you. Do not let it catch you. Do not let it catch you. Do not let it catch you. Do not let it catch you. Do not let it catch you. Do not let it catch you. Do not let it catch you. Do not let it catch you. Do not let it catch you. Do not let it catch you. Do not let it catch you. Do not let it catch you. Do not let it catch you. Do not let it catch you. Do not let it catch you. Do not let it catch you. Do not let it catch you. Do not let it catch you. Do not let it catch you. Do not let it catch you. Do not let it catch you. Do not let it catch you. Do not let it catch you. Do not let it catch you. Do not let it catch you. Do not let it catch you. Do not let it catch you. Do not let it catch you. Do not let it catch you. Do not let it catch you. Do not let it catch you. Do not let it catch you. Do \nHuge thanks to:\n \nMattPin for his PSX/CRT Retro Shader for Godot\nCrocoby for his Vignette shadeKushal for his Free Hand low-poly 3D modelAnd most of all to Pizza Doggy for his PSX Mega Pack asset pack\n\nMade by Wolan, PolskiAnt, music by Łosiu, for the 20 Second Game Jam",
        "screenshots": [
          "https://img.itch.zone/aW1hZ2UvNDA2NjU3Ni8yNDQ5MzY0OS5wbmc=/original/CPRkfQ.png",
          "https://img.itch.zone/aW1hZ2UvNDA2NjU3Ni8yNDQ5MzMyMC5wbmc=/original/yZ%2FnyY.png",
          "https://img.itch.zone/aW1hZ2UvNDA2NjU3Ni8yNDQ5MzMxOS5wbmc=/original/rVZZHq.png",
          "https://img.itch.zone/aW1hZ2UvNDA2NjU3Ni8yNDQ5MzUzOS5wbmc=/original/BGHooM.png",
          "https://img.itch.zone/aW1hZ2UvNDA2NjU3Ni8yNDQ5MzU0MC5wbmc=/original/xgr0Qn.png"
        ],
        "moreInfo": {
          "Status": "Released",
          "Platforms": "HTML5, Windows",
          "Rating": "Rated 5.0 out of 5 stars(5 total ratings)",
          "Authors": "Wolan, Polskiant",
          "Genre": "Action",
          "Made with": "Godot",
          "Tags": "Horror, PSX (PlayStation), Runner",
          "Average session": "A few minutes",
          "Inputs": "Keyboard, Mouse"
        }
      }
    },
    {
      "gameId": 4117405,
      "gameUrl": "https://poprossrocks.itch.io/got-slimed",
      "overallRank": 12,
      "topCategories": [],
      "resultData": null,
      "entryData": {
        "rating_count": 0,
        "url": "/jam/20-second-game-jam-2025/rate/4117405",
        "game": {
          "cover": "https://img.itch.zone/aW1nLzI0NTc0NTkxLnBuZw==/300x240%23c/GNtGrX.png",
          "cover_color": "#0d000e",
          "url": "https://poprossrocks.itch.io/got-slimed",
          "id": 4117405,
          "short_text": "Solve the mystery of the wizard's dungeon, 20 seconds at a time.",
          "title": "Got Slimed!",
          "user": {
            "id": 476703,
            "url": "https://poprossrocks.itch.io",
            "name": "Poprossrocks"
          },
          "platforms": [
            "web"
          ]
        },
        "created_at": "2025-12-16 00:08:02",
        "id": 808910,
        "contributors": [
          {
            "url": "https://poprossrocks.itch.io",
            "name": "Poprossrocks"
          },
          {
            "url": "https://varii-peppertangogames.itch.io",
            "name": "Varii @ PepperTangoGames"
          }
        ],
        "coolness": 0
      },
      "details": {
        "title": "Got Slimed!",
        "description": "\nGOT SLIMED!\nThis wizard needs your help! Solve the puzzle and defeat the giant evil Slime... All within 20 seconds? That cant be right...\n    \nCreated as part of the 20 Second Game Jam 2025\nCredits:- Varii and PoprossRocks - Developers and Art- PenguinSphen - Music and Sound Effects\nExternal assets used:Tilemap and CharacterBoss Sound EffectDamage Sound EffectScreen Transition Sound EffectWall Break Sound EffectClick Sound EffectInput prompt icons\n\n\n",
        "screenshots": [
          "https://img.itch.zone/aW1hZ2UvNDExNzQwNS8yNDU4MjAxNi5wbmc=/original/Fg4Q3g.png",
          "https://img.itch.zone/aW1hZ2UvNDExNzQwNS8yNDU2NzE5MC5wbmc=/original/%2BbKKSu.png",
          "https://img.itch.zone/aW1hZ2UvNDExNzQwNS8yNDU1OTQwNi5wbmc=/original/8XFDgf.png",
          "https://img.itch.zone/aW1hZ2UvNDExNzQwNS8yNDU1OTQwOC5wbmc=/original/UQSz0%2F.png"
        ],
        "moreInfo": {
          "Status": "Released",
          "Platforms": "HTML5",
          "Rating": "Rated 5.0 out of 5 stars(5 total ratings)",
          "Authors": "Poprossrocks, Varii @ PepperTangoGames",
          "Genre": "Puzzle, Action, Adventure",
          "Made with": "Unity",
          "Tags": "2D, Indie, Pixel Art, Short"
        }
      }
    },
    {
      "gameId": 4076479,
      "gameUrl": "https://kaiakairos.itch.io/plinkos-bomb-defusal",
      "overallRank": 13,
      "topCategories": [],
      "resultData": null,
      "entryData": {
        "rating_count": 0,
        "url": "/jam/20-second-game-jam-2025/rate/4076479",
        "game": {
          "cover": "https://img.itch.zone/aW1nLzI0Mjk5NTMwLnBuZw==/300x240%23c/eLzs14.png",
          "cover_color": "#000000",
          "url": "https://kaiakairos.itch.io/plinkos-bomb-defusal",
          "id": 4076479,
          "short_text": "Defuse a bomb in less than 20 seconds",
          "title": "Plinko's Bomb Defusal",
          "user": {
            "id": 3182296,
            "url": "https://kaiakairos.itch.io",
            "name": "kaiakairos"
          },
          "platforms": [
            "windows",
            "web"
          ]
        },
        "created_at": "2025-12-01 01:04:28",
        "id": 802874,
        "coolness": 0
      },
      "details": {
        "title": "Plinko's Bomb Defusal",
        "description": "Plinko needs to defuse this bomb, and he only has 20 seconds !!\nTry to solve a randomized puzzle in only 20 seconds. Once you win, try to get a faster score. There are also daily puzzles, where everyone will get the same puzzle. Repeat it as many times as you want to get the best score and beat your friends.\n\nCredits:\nkaiakairos - programmer and artist\nstaggernight - musician\nsounds sampled from Freesound.org and Titanfall\n\nMade for the:\nMCCGDC Fall Jam 2025\n20 Second Jam 2025\n\nSource Code:\nhttps://github.com/kaiakairos/plinkos-bomb-defusal\n\n\nIf you like the game consider throwing me a buck or two when you download it :)",
        "screenshots": [
          "https://img.itch.zone/aW1hZ2UvNDA3NjQ3OS8yNDI5Nzg5OS5wbmc=/original/FIDvA6.png",
          "https://img.itch.zone/aW1hZ2UvNDA3NjQ3OS8yNDI5ODE2NS5wbmc=/original/pyZ%2BWq.png"
        ],
        "moreInfo": {
          "Status": "Released",
          "Platforms": "HTML5, Windows",
          "Rating": "Rated 4.9 out of 5 stars(36 total ratings)",
          "Author": "kaiakairos",
          "Genre": "Action",
          "Made with": "Godot",
          "Tags": "2D, High Score, Time Attack"
        }
      }
    },
    {
      "gameId": 4055458,
      "gameUrl": "https://igor-cunev.itch.io/cage-in-my-head-in-my-cage-in-my-head-in-my-cage",
      "overallRank": 14,
      "topCategories": [],
      "resultData": null,
      "entryData": {
        "rating_count": 0,
        "url": "/jam/20-second-game-jam-2025/rate/4055458",
        "game": {
          "cover": "https://img.itch.zone/aW1nLzI0MTg0MzY5LnBuZw==/300x240%23c/wal%2FUe.png",
          "url": "https://igor-cunev.itch.io/cage-in-my-head-in-my-cage-in-my-head-in-my-cage",
          "id": 4055458,
          "cover_color": "#000000",
          "title": "Cage in my head in my cage in my head in my cage",
          "user": {
            "id": 13756632,
            "url": "https://igor-cunev.itch.io",
            "name": "Igor Cunev"
          },
          "platforms": [
            "web"
          ]
        },
        "created_at": "2025-11-20 22:25:53",
        "id": 798508,
        "coolness": 0
      },
      "details": {
        "title": "Cage in my head in my cage in my head in my cage",
        "description": "C̶a̴g̴e̵ ̸i̸n̷ ̶m̵y̵ ̵h̵e̶a̴d̸ ̴i̶n̷ ̴m̶y̴ ̶c̶a̵g̴e̶ ̸i̵n̸ ̸m̴y̵ ̷h̵e̷a̷d̸ ̷ ̸i̸n̷ ̴m̴y̴ ̸c̴a̴g̸e̵ ̴i̶n̵ ̴m̵y̷ ̶h̴e̴a̸d̵ ̴i̴n̸ ̵m̵y̶ ̷c̸a̵g̵e̷ ̸i̴n̶ ̷m̵y̶ ̷h̷e̷a̸d̴ ̸i̸n̵ ̵m̴y̶ ̶c̴a̵g̶e̶ ̶i̸n̸ ̷m̶y̴ ̵h̴e̴a̸d̵ ̴i̶n̶ ̷m̶y̸ ̴c̵a̵g̵e̵ ̵i̶n̵ ̶m̴y̴ ̵h̵e̵a̷d̶ ̵i̴n̷ ̷m̵y̵ ̶c̶a̴g̸e̸ ̷i̷n̷ ̷m̵y̸ ̴h̶e̷a̵d̸ ̶i̷n̷ ̵m̶y̷ ̵c̶a̷g̸e̶ ̵i̴n̵ ̸m̴y̶ ̷h̶e̵a̸d̶ ̵i̵n̸ ̵m̶y̵ ̶c̸a̸g̵e̵ ̷i̴n̷ ̸m̴y̵ ̵h̴e̴a̴d̴ ̷i̶n̵ ̷m̸y̷ ̷c̸a̸g̵e̸ ̴i̷n̸ ̶m̷y̶ ̷h̵e̷a̶d̸ ̶i̸n̸ ̶m̶y̸ ̵c̷a̴g̴e̵ ̷i̸n̴ ̵m̵y̵ ̴h̷e̶a̸d̴ ̵i̶n̵ ̵m̵y̴ ̵c̸a̴g̸e̵ ̷i̷n̷ ̴m̷y̵ ̸h̵e̷a̴d̴ ̶i̵n̸ ̵m̵y̷ ̷c̵a̴g̷e̷ ̷i̶n̴ ̵m̸y̴ ̶h̸e̸a̵d̸ ̸i̷n̷ ̴m̸y̷ ̶c̷a̶g̴e̵ ̶i̶n̵ ̵m̶y̶ ̶h̸e̴a̸d̸ ̴i̴n̵ ̶m̶y̸ ̸c̸a̴g̶e̸ ̷i̸n̴ ̶m̵y̴ ̷h̵e̶a̶d̴ ̵i̶n̸ ̶m̸y̵ ̶c̵a̸g̸e̷ ̸i̸n̷ ̵m̶y̴ ̸h̴e̶a̵d̴ ̸i̸n̸ ̷m̴y̵ ̵c̵a̵g̵e̵ ̴i̶n̷ ̸m̸y̴ ̵h̶e̸a̴d̵ ̶i̶n̷ ̵m̸y̸ ̸c̷a̴g̴e̸ ̸i̵n̴ ̵m̵y̸ ̶h̶e̶a̸d̶ ̴i̷n̴ ̵m̵y̷ ̶c̶a̶g̶e̴ ̸i̴n̸ ̴m̷y̷ ̵h̶e̴a̸d̴ ̴i̵n̴ ̸m̸y̶ ̸c̸a̸g̴e̶ ̴i̸n̵ ̷m̷y̸ ̵h̷e̴a̸d̵ ̷i̶n̶ ̵m̴y̷ ̷c̴a̷g̷e̷ ̷i̵n̷ ̵m̶y̴ ̶h̷e̷a̵d̷ ̶i̸n̸ ̶m̵y̸ ̸c̵a̷g̷e̶ ̸i̴n̴ ̵m̸y̸ ̷h̸e̵a̵d̴ ̶i̶n̴ ̵m̶y̶ ̵c̴a̷g̷e̵ ̸i̷n̴ ̵m̸y̴ ̸h̷e̴a̶d̴ ̸i̴n̸ ̴m̶y̶ ̶c̴a̶g̴e̴ ̸i̴n̵ ̸m̴y̵ ̸h̷e̴a̷d̵ ̸i̶n̸ ̷m̷y̷ ̸c̵a̵g̴e̴ ̸i̸n̶ ̸m̸y̴ ̷h̷e̷a̶d̸ ̶i̸n̵ ̴m̸y̸ ̸c̸a̸g̵e̵ ̵i̵n̵ ̸m̶y̷ ̷h̶e̷a̴d̶ ̸i̵n̷ ̴m̴y̶ ̶c̵a̵g̸e̸ ̴i̵n̵ ̸m̴y̷ ̵h̴e̶a̷d̷ ̴i̴n̶ ̶m̵y̷ ̶c̶a̶g̸e̴ ̴i̸n̴ ̷m̴y̷ ̸h̸e̷a̸d̶ ̷i̷n̵ ̶m̴y̴ ̶c̶a̴g̷e̵ ̷i̷n̴ ̷m̵y̶ ̵h̴e̶a̷d̵ ̶i̶n̸ ̸m̷y̸ ̵c̶a̸g̸e̵ ̶i̵n̶ ̴m̵y̴ ̶h̵e̴a̵d̷ ̸i̵n̴ ̷m̵y̵ ̶c̸a̶g̶e̸ ̸i̴n̸ ̴m̷y̴ ̷h̴e̸a̴d̵ ̸i̵n̵ ̷m̶y̷ ̸c̵a̷g̵e̸ ̴i̶n̵ ̶m̶y̷ ̸h̵e̷a̵d̷ ̶i̸n̵ ̷m̵y̴ ̸c̴a̷g̷e̶ ̷i̶n̶ ̸m̴y̷ ̷h̴e̴a̵d̵ ̵i̴n̴ ̸m̷y̴ ̶c̴a̸g̴e̶ ̶i̶n̸ ̶m̷y̵ ̵h̴e̴a̴d̸ ̸i̸n̶ ̴m̴y̴ ̷c̴a̸g̸e̸ ̵i̶n̴ ̷m̷y̶ ̷h̶e̶a̵d̶ ̶i̵n̴ ̵m̸y̶ ̸c̷a̸g̵e̴ ̸i̸n̶ ̵m̷y̵ ̸h̶e̴a̷d̶ ̶i̸n̸ ̸m̴y̶ ̶c̷a̴g̷e̸ ̵i̸n̸ ̸m̶y̸ ̴h̶e̵a̶d̵ ̷i̵n̵ ̴m̶y̷ ̵c̵a̷g̴e̶ ̴i̶n̶ ̴m̵y̵ ̷h̸e̶a̶d̴ ̸i̵n̴ ̴m̴y̸ ̴c̴a̷g̷e̴ ̴i̴n̴ ̴m̴y̸ ̷h̶e̵a̸d̸ ̵i̴n̶ ̸m̷y̴ ̷c̵a̶g̶e̵ ̴i̴n̷ ̷m̷y̷ ̸h̵e̴a̵d̵ ̵i̴n̵ ̴m̵y̸ ̶c̴a̴g̴e̸ ̴i̶n̸ ̶m̸y̸ ̸h̵e̶a̵d̴ ̷i̶n̸ ̵m̸y̴ ̵c̷a̴g̴e̶ ̴i̶n̸ ̴m̴y̸ ̷h̸e̶a̵d̵ ̸i̷n̸ ̶m̸y̷ ̷c̵a̶g̴e̶ ̷i̸n̴ ̶m̷y̸ ̶h̶e̵a̷d̶ ̴i̶n̵ ̵m̶y̶ ̵c̷a̷g̴e̴ ̵i̴n̶ ̵m̴y̶ ̵h̴e̷a̵d̸ ̸i̴n̷ ̸m̴y̸ ̵c̵a̷g̶e̸ ̴i̶n̷ ̵m̷y̴ ̶h̵e̶a̶d̵ ̴i̵n̸ ̷m̴y̸ ̸c̴a̵g̵e̸ ̵i̸n̶ ̶m̶y̴ ̸h̸e̴a̵d̴ ̴i̶n̷ ̸m̷y̷ ̶c̶a̵g̸e̴ ̶i̷n̶ ̷m̷y̷ ̴h̸e̶a̶d̸ ̴i̵n̵ ̶m̷y̶ ̸c̴a̶g̷e̶ ̵i̷n̴ ̴m̶y̵ ̵h̴e̵a̸d̸ ̴i̶n̷ ̵m̶y̸ ̶c̶a̴g̵e̷ ̵i̴n̷ ̴m̷y̸ ̶h̷e̵a̸d̶ ̸i̷n̷ ̶m̶y̶ ̸c̷a̸g̶e̷ ̸i̷n̵ ̶m̵y̴ ̶h̷e̵a̷d̶ ̵i̴n̶ ̸m̷y̷ ̵c̵a̴g̶e̶ ̴i̵n̵ ̶m̴y̶ ̶h̸e̵a̶d̴ ̸i̵n̵ ̷m̴y̵ ̵c̴a̸g̵e̵ ̵i̶n̶ ̵m̵y̵ ̴h̶e̸a̵d̶ ̶i̷n̸ ̶m̵y̵ ̴c̷a̵g̸e̴ ̶i̴n̶ ̸m̵y̴ ̶h̵e̸a̴d̸ ̷i̸n̸ ̵m̸y̴ ̶c̵a̶g̸e̶ ̵i̸n̶ ̸m̵y̷ ̷h̴e̵a̴d̷ ̸i̶n̷ ̵m̵y̷ ̶c̵a̷g̶e̵ ̸i̷n̷ ̵m̵y̴ ̷h̶e̶a̶d̴ ̵i̷n̶ ̷m̶y̴ ̶c̴a̶g̵e̸ ̷i̷n̵ ̷m̵y̸ ̷h̴e̷a̶d̶ ̷i̸n̷ ̶m̸y̴ ̴c̸a̶g̶e̷ ̸i̶n̷ ̶m̷y̸ ̴h̵e̷a̷d̶ ̴i̴n̶ ̴m̵y̵ ̸c̶a̶g̴e̵ ̷i̷n̵ ̶m̶y̴ ̶h̵e̸a̶d̴ ̶i̵n̸ ̴m̷y̴ ̵c̵a̵g̴e̸ ̶i̴n̵ ̴m̷y̷ ̷h̷e̴a̵d̷ ̶i̶n̷ ̷m̵y̶ ̶c̴a̷g̷e̷ ̶i̵n̷ ̵m̵y̴ ̵h̷e̷a̴d̸ ̸i̴n̵ ̸m̵y̶ ̵c̷a̷g̶e̴ ̵i̴n̸ ̸m̵y̶ ̷h̵e̴a̸d̶ ̶i̵n̵ ̴m̴y̵ ̴c̴a̸g̸e̶ ̶i̶n̶ ̸m̷y̷ ̸h̶e̵a̴d̸ ̵i̷n̵ ̷m̸y̶ ̶c̶a̷g̶e̷ ̸i̷n̵ ̶m̴y̶ ̶h̷e̶a̵d̵ ̶i̵n̴ ̵m̷y̵ ̷c̶a̴g̴e̸ ̸i̸n̴ ̵m̶y̵ ̵h̵e̴a̵d̸ ̴i̵n̶ ̷m̷y̶ ̴c̴a̸g̸e̸ ̸i̷n̴ ̶m̸y̷ ̵h̷e̷a̵d̸ ̵i̴n̴ ̶m̷y̴ ̷c̶a̷g̴e̶ ̶i̷n̸ ̶m̵y̵ ̶h̶e̶a̷d̸ ̸i̸n̸ ̶m̴y̶ ̵c̷a̶g̸e̸ ̴i̸n̸ ̶m̷y̴ ̷h̸e̶a̶d̷ ̴i̸n̷ ̷m̴y̶ ̴c̴a̸g̴e̵ ̵i̸n̷ ̷m̶y̴ ̴h̸e̶a̵d̷ ̷i̶n̵ ̵m̷y̵ ̷c̶a̴g̷e̸ ̸i̶n̷ ̵m̸y̸ ̷h̴e̵a̵d̸ ̸i̷n̸ ̸m̸y̴ ̵c̸a̵g̵e̵ ̵i̵n̸ ̷m̶y̴ ̷h̴e̵a̵d̷ ̴i̷n̴ ̴m̵y̴ ̴c̵a̷g̴e̶ ̷i̸n̵ ̷m̶y̵ ̶h̵e̴a̷d̵ ̷i̵n̴ ̵m̵y̷ ̵c̵a̶g̸e̵ ̸i̷n̷ ̶m̵y̴ ̴h̷e̸a̷d̴ ̶i̴n̸ ̴m̸y̶ ̷c̷a̶g̷e̸ ̵i̴n̶ ̷m̸y̸ ̵h̵e̵a̷d̸ ̷i̷n̷ ̸m̸y̴ ̸c̷a̴g̸e̶ ̶i̷n̶ ̴m̸y̴ ̶h̸e̴a̷d̶ ̵i̶n̷ ̷m̸y̵ ̴c̴a̸g̴e̴ ̴i̸n̸ ̶m̵y̵ ̶h̸e̶a̸d̸ ̷i̸n̶ ̷m̸y̴ ̶c̸a̸g̷e̷ ̴i̴n̷ ̶m̶y̷ ̶h̴e̶a̵d̴ ̷i̴n̷ ̵m̷y̴ ̴c̷a̵g̴e̴ ̴i̷n̸ ̶m̶y̴ ̵h̸e̷a̷d̷ ̴i̴n̴ ̷m̵y̶ ̶c̵a̸g̷e̶ ̴i̶n̴ ̵m̴y̸ ̵h̶e̶a̵d̴ ̷i̶n̸ ̵m̷y̴ ̸c̸a̵g̸e̶ ̷i̸n̶ ̴m̵y̶ ̶h̷e̵a̵d̵ ̵i̷n̶ ̸m̵y̸ ̴c̴a̴g̷e̵ ̸i̶n̵ ̸m̵y̷ ̴h̵e̶a̷d̵ ̴i̴n̷ ̷m̸y̸ ̶c̷a̶g̷e̷ ̸i̴n̵ ̸m̶y̶ ̷h̷e̶a̶d̶ ̵i̶n̵ ̷m̴y̵ ̶c̷a̵g̴e̴ ̸i̷n̶ ̷m̸y̵ ̶h̴e̸a̸d̵ ̸i̷n̴ ̶m̷y̴ ̶c̴a̶g̷e̶ ̷i̴n̸ ̴m̷y̵ ̸h̸e̵a̷d̶ ̷i̷n̷ ̸m̵y̷ ̵c̶a̵g̶e̵ ̵i̶n̸ ̶m̶y̵ ̴h̶e̸a̶d̴ ̸i̴n̶ ̵m̵y̷ ̴c̶a̸g̴e̸ ̶i̸n̶ ̷m̴y̴ ̷h̷e̸a̵d̶ ̷i̷n̶ ̷m̵y̷ ̴c̵a̴g̵e̶ ̵i̴n̶ ̸m̷y̷ ̶h̵e̴a̸d̸ ̷i̴n̸ ̶m̸y̵ ̸c̵a̴g̸e̵ ̷i̷n̸ ̴m̷y̶ ̴h̶e̵a̷d̵ ̸i̴n̵ ̷m̵y̷ ̶c̸a̵g̵e̷ ̶i̶n̴ ̵m̶y̵ ̵h̵e̴a̸d̸ ̷i̵n̷ ̶m̴y̴ ̷c̸a̴g̸e̸ ̴i̷n̷ ̵m̸y̴ ̴h̷e̶a̴d̷ ̵i̴n̴ ̴m̶y̷ ̸c̷a̵g̸e̶ ̵i̶n̴ ̸m̸y̷ ̵h̴e̵a̸d̶ ̸i̸n̵ ̸m̷y̴ ̶c̴a̸g̸e̴ ̴i̶n̶ ̸m̴y̸ ̵h̷e̸a̴d̸ ̸i̴n̷ ̴m̴y̵ ̷c̷a̷g̵e̵ ̸i̸n̷ ̴m̴y̵ ̵h̷e̵a̵d̶ ̵i̷n̴ ̶m̸y̶ ̷c̶a̴g̸e̸ ̸i̵n̸ ̶m̴y̵ ̸h̶e̷a̵d̶ ̸i̶n̴ ̶m̴y̶ ̶c̶a̵g̷e̶ ̷i̴n̷ ̴m̵y̴ ̷h̸e̸a̶d̸ ̸i̴n̶ ̷m̶y̵ ̸c̵a̷g̵e̸ ̵i̶n̴ ̴m̴y̸ ̵h̷e̵a̷d̸ ̵i̴n̸ ̶m̴y̸ ̴c̷a̴g̷e̵ ̷i̷n̴ ̵m̸y̵ ̴h̴e̸a̶d̸ ̶i̵n̴ ̷m̶y̷ ̷c̷a̷g̴e̸ ̷i̵n̶ ̴m̷y̶ ̴h̵e̴a̷d̷ ̶i̷n̸ ̸m̶y̴ ̵c̶a̷g̷e̶ ̸i̸n̸ ̴m̴y̸ ̶h̵e̴a̵d̷ ̶i̷n̵ ̸m̵y̷ ̸c̴a̸g̴e̵ ̴i̸n̸ ̵m̵y̵ ̴h̸e̷a̶d̵ ̵i̸n̷ ̶m̴y̷ ̴c̵a̷g̴e̴ ̶i̵n̶ ̸m̸y̴ ̴h̶e̶a̸d̸ i̶n̷ ̴m̶y̴ ̶c̶a̵g̴e̶ ̸i̵n̸ ̸m̴y̵ ̷h̵e̷a̷d̸ ̷ ̸i̸n̷ ̴m̴y̴ ̸c̴a̴g̸e̵ ̴i̶n̵ ̴m̵y̷ ̶h̴e̴a̸d̵ ̴i̴n̸ ̵m̵y̶ ̷c̸a̵g̵e̷ ̸i̴n̶ ̷m̵y̶ ̷h̷e̷a̸d̴ ̸i̸n̵ ̵m̴y̶ ̶c̴a̵g̶e̶ ̶i̸n̸ ̷m̶y̴ ̵h̴e̴a̸d̵ ̴i̶n̶ ̷m̶y̸ ̴c̵a̵g̵e̵ ̵i̶n̵ ̶m̴y̴ ̵h̵e̵a̷d̶ ̵i̴n̷ ̷m̵y̵ ̶c̶a̴g̸e̸ ̷i̷n̷ ̷m̵y̸ ̴h̶e̷a̵d̸ ̶i̷n̷ ̵m̶y̷ ̵c̶a̷g̸e̶ ̵i̴n̵ ̸m̴y̶ ̷h̶e̵a̸d̶ ̵i̵n̸ ̵m̶y̵ ̶c̸a̸g̵e̵ ̷i̴n̷ ̸m̴y̵ ̵h̴e̴a̴d̴ ̷i̶n̵ ̷m̸y̷ ̷c̸a̸g̵e̸ ̴i̷n̸ ̶m̷y̶ ̷h̵e̷a̶d̸ ̶i̸n̸ ̶m̶y̸ ̵c̷a̴g̴e̵ ̷i̸n̴ ̵m̵y̵ ̴h̷e̶a̸d̴ ̵i̶n̵ ̵m̵y̴ ̵c̸a̴g̸e̵ ̷i̷n̷ ̴m̷y̵ ̸h̵e̷a̴d̴ ̶i̵n̸ ̵m̵y̷ ̷c̵a̴g̷e̷ ̷i̶n̴ ̵m̸y̴ ̶h̸e̸a̵d̸ ̸i̷n̷ ̴m̸y̷ ̶c̷a̶g̴e̵ ̶i̶n̵ ̵m̶y̶ ̶h̸e̴a̸d̸ ̴i̴n̵ ̶m̶y̸ ̸c̸a̴g̶e̸ ̷i̸n̴ ̶m̵y̴ ̷h̵e̶a̶d̴ ̵i̶n̸ ̶m̸y̵ ̶c̵a̸g̸e̷ ̸i̸n̷ ̵m̶y̴ ̸h̴e̶a̵d̴ ̸i̸n̸ ̷m̴y̵ ̵c̵a̵g̵e̵ ̴i̶n̷ ̸m̸y̴ ̵h̶e̸a̴d̵ ̶i̶n̷ ̵m̸y̸ ̸c̷a̴g̴e̸ ̸i̵n̴ ̵m̵y̸ ̶h̶e̶a̸d̶ ̴i̷n̴ ̵m̵y̷ ̶c̶a̶g̶e̴ ̸i̴n̸ ̴m̷y̷ ̵h̶e̴a̸d̴ ̴i̵n̴ ̸m̸y̶ ̸c̸a̸g̴e̶ ̴i̸n̵ ̷m̷y̸ ̵h̷e̴a̸d̵ ̷i̶n̶ ̵m̴y̷ ̷c̴a̷g̷e̷ ̷i̵n̷ ̵m̶y̴ ̶h̷e̷a̵d̷ ̶i̸n̸ ̶m̵y̸ ̸c̵a̷g̷e̶ ̸i̴n̴ ̵m̸y̸ ̷h̸e̵a̵d̴ ̶i̶n̴ ̵m̶y̶ ̵c̴a̷g̷e̵ ̸i̷n̴ ̵m̸y̴ ̸h̷e̴a̶d̴ ̸i̴n̸ ̴m̶y̶ ̶c̴a̶g̴e̴ ̸i̴n̵ ̸m̴y̵ ̸h̷e̴a̷d̵ ̸i̶n̸ ̷m̷y̷ ̸c̵a̵g̴e̴ ̸i̸n̶ ̸m̸y̴ ̷h̷e̷a̶d̸ ̶i̸n̵ ̴m̸y̸ ̸c̸a̸g̵e̵ ̵i̵n̵ ̸m̶y̷ ̷h̶e̷a̴d̶ ̸i̵n̷ ̴m̴y̶ ̶c̵a̵g̸e̸ ̴i̵n̵ ̸m̴y̷ ̵h̴e̶a̷d̷ ̴i̴n̶ ̶m̵y̷ ̶c̶a̶g̸e̴ ̴i̸n̴ ̷m̴y̷ ̸h̸e̷a̸d̶ ̷i̷n̵ ̶m̴y̴ ̶c̶a̴g̷e̵ ̷i̷n̴ ̷m̵y̶ ̵h̴e̶a̷d̵ ̶i̶n̸ ̸m̷y̸ ̵c̶a̸g̸e̵ ̶i̵n̶ ̴m̵y̴ ̶h̵e̴a̵d̷ ̸i̵n̴ ̷m̵y̵ ̶c̸a̶g̶e̸ ̸i̴n̸ ̴m̷y̴ ̷h̴e̸a̴d̵ ̸i̵n̵ ̷m̶y̷ ̸c̵a̷g̵e̸ ̴i̶n̵ ̶m̶y̷ ̸h̵e̷a̵d̷ ̶i̸n̵ ̷m̵y̴ ̸c̴a̷g̷e̶ ̷i̶n̶ ̸m̴y̷ ̷h̴e̴a̵d̵ ̵i̴n̴ ̸m̷y̴ ̶c̴a̸g̴e̶ ̶i̶n̸ ̶m̷y̵ ̵h̴e̴a̴d̸ ̸i̸n̶ ̴m̴y̴ ̷c̴a̸g̸e̸ ̵i̶n̴ ̷m̷y̶ ̷h̶e̶a̵d̶ ̶i̵n̴ ̵m̸y̶ ̸c̷a̸g̵e̴ ̸i̸n̶ ̵m̷y̵ ̸h̶e̴a̷d̶ ̶i̸n̸ ̸m̴y̶ ̶c̷a̴g̷e̸ ̵i̸n̸ ̸m̶y̸ ̴h̶e̵a̶d̵ ̷i̵n̵ ̴m̶y̷ ̵c̵a̷g̴e̶ ̴i̶n̶ ̴m̵y̵ ̷h̸e̶a̶d̴ ̸i̵n̴ ̴m̴y̸ ̴c̴a̷g̷e̴ ̴i̴n̴ ̴m̴y̸ ̷h̶e̵a̸d̸ ̵i̴n̶ ̸m̷y̴ ̷c̵a̶g̶e̵ ̴i̴n̷ ̷m̷y̷ ̸h̵e̴a̵d̵ ̵i̴n̵ ̴m̵y̸ ̶c̴a̴g̴e̸ ̴i̶n̸ ̶m̸y̸ ̸h̵e̶a̵d̴ ̷i̶n̸ ̵m̸y̴ ̵c̷a̴g̴e̶ ̴i̶n̸ ̴m̴y̸ ̷h̸e̶a̵d̵ ̸i̷n̸ ̶m̸y̷ ̷c̵a̶g̴e̶ ̷i̸n̴ ̶m̷y̸ ̶h̶e̵a̷d̶ ̴i̶n̵ ̵m̶y̶ ̵c̷a̷g̴e̴ ̵i̴n̶ ̵m̴y̶ ̵h̴e̷a̵d̸ ̸i̴n̷ ̸m̴y̸ ̵c̵a̷g̶e̸ ̴i̶n̷ ̵m̷y̴ ̶h̵e̶a̶d̵ ̴i̵n̸ ̷m̴y̸ ̸c̴a̵g̵e̸ ̵i̸n̶ ̶m̶y̴ ̸h̸e̴a̵d̴ ̴i̶n̷ ̸m̷y̷ ̶c̶a̵g̸e̴ ̶i̷n̶ ̷m̷y̷ ̴h̸e̶a̶d̸ ̴i̵n̵ ̶m̷y̶ ̸c̴a̶g̷e̶ ̵i̷n̴ ̴m̶y̵ ̵h̴e̵a̸d̸ ̴i̶n̷ ̵m̶y̸ ̶c̶a̴g̵e̷ ̵i̴n̷ ̴m̷y̸ ̶h̷e̵a̸d̶ ̸i̷n̷ ̶m̶y̶ ̸c̷a̸g̶e̷ ̸i̷n̵ ̶m̵y̴ ̶h̷e̵a̷d̶ ̵i̴n̶ ̸m̷y̷ ̵c̵a̴g̶e̶ ̴i̵n̵ ̶m̴y̶ ̶h̸e̵a̶d̴ ̸i̵n̵ ̷m̴y̵ ̵c̴a̸g̵e̵ ̵i̶n̶ ̵m̵y̵ ̴h̶e̸a̵d̶ ̶i̷n̸ ̶m̵y̵ ̴c̷a̵g̸e̴ ̶i̴n̶ ̸m̵y̴ ̶h̵e̸a̴d̸ ̷i̸n̸ ̵m̸y̴ ̶c̵a̶g̸e̶ ̵i̸n̶ ̸m̵y̷ ̷h̴e̵a̴d̷ ̸i̶n̷ ̵m̵y̷ ̶c̵a̷g̶e̵ ̸i̷n̷ ̵m̵y̴ ̷h̶e̶a̶d̴ ̵i̷n̶ ̷m̶y̴ ̶c̴a̶g̵e̸ ̷i̷n̵ ̷m̵y̸ ̷h̴e̷a̶d̶ ̷i̸n̷ ̶m̸y̴ ̴c̸a̶g̶e̷ ̸i̶n̷ ̶m̷y̸ ̴h̵e̷a̷d̶ ̴i̴n̶ ̴m̵y̵ ̸c̶a̶g̴e̵ ̷i̷n̵ ̶m̶y̴ ̶h̵e̸a̶d̴ ̶i̵n̸ ̴m̷y̴ ̵c̵a̵g̴e̸ ̶i̴n̵ ̴m̷y̷ ̷h̷e̴a̵d̷ ̶i̶n̷ ̷m̵y̶ ̶c̴a̷g̷e̷ ̶i̵n̷ ̵m̵y̴ ̵h̷e̷a̴d̸ ̸i̴n̵ ̸m̵y̶ ̵c̷a̷g̶e̴ ̵i̴n̸ ̸m̵y̶ ̷h̵e̴a̸d̶ ̶i̵n̵ ̴m̴y̵ ̴c̴a̸g̸e̶ ̶i̶n̶ ̸m̷y̷ ̸h̶e̵a̴d̸ ̵i̷n̵ ̷m̸y̶ ̶c̶a̷g̶e̷ ̸i̷n̵ ̶m̴y̶ ̶h̷e̶a̵d̵ ̶i̵n̴ ̵m̷y̵ ̷c̶a̴g̴e̸ ̸i̸n̴ ̵m̶y̵ ̵h̵e̴a̵d̸ ̴i̵n̶ ̷m̷y̶ ̴c̴a̸g̸e̸ ̸i̷n̴ ̶m̸y̷ ̵h̷e̷a̵d̸ ̵i̴n̴ ̶m̷y̴ ̷c̶a̷g̴e̶ ̶i̷n̸ ̶m̵y̵ ̶h̶e̶a̷d̸ ̸i̸n̸ ̶m̴y̶ ̵c̷a̶g̸e̸ ̴i̸n̸ ̶m̷y̴ ̷h̸e̶a̶d̷ ̴i̸n̷ ̷m̴y̶ ̴c̴a̸g̴e̵ ̵i̸n̷ ̷m̶y̴ ̴h̸e̶a̵d̷ ̷i̶n̵ ̵m̷y̵ ̷c̶a̴g̷e̸ ̸i̶n̷ ̵m̸y̸ ̷h̴e̵a̵d̸ ̸i̷n̸ ̸m̸y̴ ̵c̸a̵g̵e̵ ̵i̵n̸ ̷m̶y̴ ̷h̴e̵a̵d̷ ̴i̷n̴ ̴m̵y̴ ̴c̵a̷g̴e̶ ̷i̸n̵ ̷m̶y̵ ̶h̵e̴a̷d̵ ̷i̵n̴ ̵m̵y̷ ̵c̵a̶g̸e̵ ̸i̷n̷ ̶m̵y̴ ̴h̷e̸a̷d̴ ̶i̴n̸ ̴m̸y̶ ̷c̷a̶g̷e̸ ̵i̴n̶ ̷m̸y̸ ̵h̵e̵a̷d̸ ̷i̷n̷ ̸m̸y̴ ̸c̷a̴g̸e̶ ̶i̷n̶ ̴m̸y̴ ̶h̸e̴a̷d̶ ̵i̶n̷ ̷m̸y̵ ̴c̴a̸g̴e̴ ̴i̸n̸ ̶m̵y̵ ̶h̸e̶a̸d̸ ̷i̸n̶ ̷m̸y̴ ̶c̸a̸g̷e̷ ̴i̴n̷ ̶m̶y̷ ̶h̴e̶a̵d̴ ̷i̴n̷ ̵m̷y̴ ̴c̷a̵g̴e̴ ̴i̷n̸ ̶m̶y̴ ̵h̸e̷a̷d̷ ̴i̴n̴ ̷m̵y̶ ̶c̵a̸g̷e̶ ̴i̶n̴ ̵m̴y̸ ̵h̶e̶a̵d̴ ̷i̶n̸ ̵m̷y̴ ̸c̸a̵g̸e̶ ̷i̸n̶ ̴m̵y̶ ̶h̷e̵a̵d̵ ̵i̷n̶ ̸m̵y̸ ̴c̴a̴g̷e̵ ̸i̶n̵ ̸m̵y̷ ̴h̵e̶a̷d̵ ̴i̴n̷ ̷m̸y̸ ̶c̷a̶g̷e̷ ̸i̴n̵ ̸m̶y̶ ̷h̷e̶a̶d̶ ̵i̶n̵ ̷m̴y̵ ̶c̷a̵g̴e̴ ̸i̷n̶ ̷m̸y̵ ̶h̴e̸a̸d̵ ̸i̷n̴ ̶m̷y̴ ̶c̴a̶g̷e̶ ̷i̴n̸ ̴m̷y̵ ̸h̸e̵a̷d̶ ̷i̷n̷ ̸m̵y̷ ̵c̶a̵g̶e̵ ̵i̶n̸ ̶m̶y̵ ̴h̶e̸a̶d̴ ̸i̴n̶ ̵m̵y̷ ̴c̶a̸g̴e̸ ̶i̸n̶ ̷m̴y̴ ̷h̷e̸a̵d̶ ̷i̷n̶ ̷m̵y̷ ̴c̵a̴g̵e̶ ̵i̴n̶ ̸m̷y̷ ̶h̵e̴a̸d̸ ̷i̴n̸ ̶m̸y̵ ̸c̵a̴g̸e̵ ̷i̷n̸ ̴m̷y̶ ̴h̶e̵a̷d̵ ̸i̴n̵ ̷m̵y̷ ̶c̸a̵g̵e̷ ̶i̶n̴ ̵m̶y̵ ̵h̵e̴a̸d̸ ̷i̵n̷ ̶m̴y̴ ̷c̸a̴g̸e̸ ̴i̷n̷ ̵m̸y̴ ̴h̷e̶a̴d̷ ̵i̴n̴ ̴m̶y̷ ̸c̷a̵g̸e̶ ̵i̶n̴ ̸m̸y̷ ̵h̴e̵a̸d̶ ̸i̸n̵ ̸m̷y̴ ̶c̴a̸g̸e̴ ̴i̶n̶ ̸m̴y̸ ̵h̷e̸a̴d̸ ̸i̴n̷ ̴m̴y̵ ̷c̷a̷g̵e̵ ̸i̸n̷ ̴m̴y̵ ̵h̷e̵a̵d̶ ̵i̷n̴ ̶m̸y̶ ̷c̶a̴g̸e̸ ̸i̵n̸ ̶m̴y̵ ̸h̶e̷a̵d̶ ̸i̶n̴ ̶m̴y̶ ̶c̶a̵g̷e̶ ̷i̴n̷ ̴m̵y̴ ̷h̸e̸a̶d̸ ̸i̴n̶ ̷m̶y̵ ̸c̵a̷g̵e̸ ̵i̶n̴ ̴m̴y̸ ̵h̷e̵a̷d̸ ̵i̴n̸ ̶m̴y̸ ̴c̷a̴g̷e̵ ̷i̷n̴ ̵m̸y̵ ̴h̴e̸a̶d̸ ̶i̵n̴ ̷m̶y̷ ̷c̷a̷g̴e̸ ̷i̵n̶ ̴m̷y̶ ̴h̵e̴a̷d̷ ̶i̷n̸ ̸m̶y̴ ̵c̶a̷g̷e̶ ̸i̸n̸ ̴m̴y̸ ̶h̵e̴a̵d̷ ̶i̷n̵ ̸m̵y̷ ̸c̴a̸g̴e̵ ̴i̸n̸ ̵m̵y̵ ̴h̸e̷a̶d̵ ̵i̸n̷ ̶m̴y̷ ̴c̵a̷g̴e̴ ̶i̵n̶ ̸m̸y̴ ̴h̶e̶a̸d̸.̵\n\n\n\n\n\n\n\n\n\nIf you scrolled to this point - congratulations, you got out of the loop. You have only 20 SECONDS to help me keep IT in CAGE.\nPLEASE HELP!\n\nGame was made for 20 seconds jam (20 Second Game Jam 2025 - itch.io).\n\nHope you'll enjoy it :)",
        "screenshots": [
          "https://img.itch.zone/aW1nLzI0MTg0MzY5LnBuZw==/original/nR1ZB5.png"
        ],
        "moreInfo": {
          "Status": "Released",
          "Platforms": "HTML5",
          "Rating": "Rated 4.6 out of 5 stars(15 total ratings)",
          "Author": "Igor Cunev",
          "Genre": "Visual Novel, Simulation",
          "Made with": "Ren'Py",
          "Tags": "Adult, Atmospheric, Creepy, Horror, Indie, psychedelic, Psychological Horror, Survival Horror"
        }
      }
    },
    {
      "gameId": 4094716,
      "gameUrl": "https://wenzgame.itch.io/boba-tanuki",
      "overallRank": 15,
      "topCategories": [],
      "resultData": null,
      "entryData": {
        "rating_count": 0,
        "url": "/jam/20-second-game-jam-2025/rate/4094716",
        "game": {
          "cover": "https://img.itch.zone/aW1nLzI0NjA5OTQwLnBuZw==/300x240%23c/iKJQ3z.png",
          "cover_color": "#987B6B",
          "url": "https://wenzgame.itch.io/boba-tanuki",
          "id": 4094716,
          "short_text": "Ultimate Chill Game - You are a tanuki selling boba tea to make people happy",
          "title": "Boba Tanuki",
          "user": {
            "id": 13034609,
            "url": "https://wenzgame.itch.io",
            "name": "wenz"
          },
          "platforms": [
            "windows",
            "android",
            "web"
          ]
        },
        "created_at": "2025-12-14 10:27:57",
        "id": 807927,
        "coolness": 0
      },
      "details": {
        "title": "Boba Tanuki",
        "description": "\n20sec Game Jam Team\n\nGame Developer | UX/UI : wenz\n2D Artist : serpemona\n\nTanuki Friend Jam Collab\nThe Ronin : 1Ronin Vs 1000Samurai\nBig Eye Girl : Don't Stare",
        "screenshots": [
          "https://img.itch.zone/aW1hZ2UvNDA5NDcxNi8yNDUwMDk0MS5wbmc=/original/Vu8u2x.png",
          "https://img.itch.zone/aW1hZ2UvNDA5NDcxNi8yNDUwMDk0Mi5wbmc=/original/TtU6VG.png",
          "https://img.itch.zone/aW1hZ2UvNDA5NDcxNi8yNDUwMDkzOS5wbmc=/original/inWdEE.png",
          "https://img.itch.zone/aW1hZ2UvNDA5NDcxNi8yNDUwMDk0MC5wbmc=/original/4hhu%2B5.png",
          "https://img.itch.zone/aW1hZ2UvNDA5NDcxNi8yNDU0NzU5MC5wbmc=/original/Trl3kS.png"
        ],
        "moreInfo": {
          "Status": "Prototype",
          "Platforms": "HTML5, Windows, Android",
          "Rating": "Rated 5.0 out of 5 stars(7 total ratings)",
          "Author": "wenz",
          "Genre": "Simulation",
          "Made with": "Unity",
          "Tags": "2D, boba, boba-tea, chill, Dreams, global, Global Game Jam, Singleplayer, tanuki"
        }
      }
    }
  ]
}