{
  "n": 81,
  "name": "Bigmode Game Jam 2026",
  "url": "https://itch.io/jam/bigmode-game-jam-2026",
  "theme": "SLICK",
  "slug": "bigmode-game-jam-2026",
  "jamMeta": {
    "jamType": "ended",
    "ratings": "14,895",
    "entries": "648",
    "title": "Bigmode Game Jam 2026",
    "jamURL": "https://itch.io/jam/bigmode-game-jam-2026",
    "hosts": {
      "BIGMODEsean": "https://bigmodesean.itch.io",
      "BIGMODEben": "https://bigmodeben.itch.io"
    },
    "jamID": "413385"
  },
  "totalEntries": 643,
  "ranked": false,
  "hasCategories": false,
  "needsManualSelection": true,
  "categories": [],
  "topGames": [
    {
      "gameId": 4266022,
      "gameUrl": "https://lm-8.itch.io/slick-game-by-slicknick12",
      "overallRank": 1,
      "topCategories": [],
      "resultData": null,
      "entryData": {
        "url": "/jam/bigmode-game-jam-2026/rate/4266022",
        "id": 829586,
        "created_at": "2026-02-07 15:51:27",
        "rating_count": 26,
        "game": {
          "title": "SLICK GAME by SlickNick12",
          "cover_color": "#2f97ff",
          "url": "https://lm-8.itch.io/slick-game-by-slicknick12",
          "id": 4266022,
          "user": {
            "id": 10982466,
            "url": "https://lm-8.itch.io",
            "name": "L.M."
          },
          "cover": "https://img.itch.zone/aW1nLzI1NDQ3NzcxLnBuZw==/300x240%23c/tWn5bN.png",
          "short_text": "Go through the files, find a link and a code  untill... \"The End\""
        },
        "coolness": 646
      },
      "details": {
        "title": "SLICK GAME by SlickNick12",
        "description": "SLICK GAME by SlickNick12 is a SLICK GAME\nin this \"game\" you are going through the game files of a video game. and what you need to do is to find 2 things:\na linkanda code ( password )in said files of said \"game\"so yeahthats all you have to knowEnjoy!also SlickNick12 is not a real person (at least this one)the \"game\" was made by L.M. and vaery small help with some other people it's just a file",
        "screenshots": [
          "https://img.itch.zone/aW1hZ2UvNDI2NjAyMi8yNTQ0Nzg0Mi5wbmc=/original/xFD7IO.png"
        ],
        "moreInfo": {
          "Updated": "19 days ago",
          "Status": "Released",
          "Author": "L.M.",
          "Genre": "Adventure, Interactive Fiction, Puzzle",
          "Tags": "Comedy, Indie, Mystery, Narrative, secrets, Singleplayer, slick"
        }
      }
    },
    {
      "gameId": 4267976,
      "gameUrl": "https://peterstubbs.itch.io/target-smash",
      "overallRank": 2,
      "topCategories": [],
      "resultData": null,
      "entryData": {
        "url": "/jam/bigmode-game-jam-2026/rate/4267976",
        "id": 829810,
        "created_at": "2026-02-07 22:52:46",
        "rating_count": 66,
        "game": {
          "title": "TARGET SMASH!",
          "cover_color": "#020307",
          "url": "https://peterstubbs.itch.io/target-smash",
          "id": 4267976,
          "platforms": [
            "web"
          ],
          "cover": "https://img.itch.zone/aW1nLzI1NDM3NjA1LnBuZw==/300x240%23c/fgnXVh.png",
          "user": {
            "id": 36178,
            "url": "https://peterstubbs.itch.io",
            "name": "PeterStubbs"
          }
        },
        "coolness": 396
      },
      "details": {
        "title": "TARGET SMASH!",
        "description": "Run and Slide through levels while sharp shooting targets to rack up a combo. Proform flips, wall jumps, use your grapple chain, and gun to get S rank in 3 levels!\n\nThis game was made for the Big Mode game Jam, though I was visiting my lovley girlfriend for the most of it so it was pushed out in 3 days. \nPlease enjoy and leave a comment with ur times and ranks <3  Controls:\nWASD - Movement\nMouse - Aim/ShootR - Quick Restart Stage  Credits: (Music)\nVaerionii    -BY Gobusto\n[https://opengameart.org/content/vaerion-side-scrolling-shooter-music]\nSkyFire (Title Screen)   -BY Oblidivm\n[https://opengameart.org/content/space-shooter-music]",
        "screenshots": [
          "https://img.itch.zone/aW1hZ2UvNDI2Nzk3Ni8yNTQ1NzI1NS5naWY=/original/AtMbLA.gif",
          "https://img.itch.zone/aW1hZ2UvNDI2Nzk3Ni8yNTQzNzc5MS5wbmc=/original/%2BknVYs.png",
          "https://img.itch.zone/aW1hZ2UvNDI2Nzk3Ni8yNTQzNzc5NC5wbmc=/original/xDz6D7.png",
          "https://img.itch.zone/aW1hZ2UvNDI2Nzk3Ni8yNTQzNzc5Mi5wbmc=/original/Blfwtl.png",
          "https://img.itch.zone/aW1hZ2UvNDI2Nzk3Ni8yNTQzNzc5My5wbmc=/original/2tP%2FsT.png"
        ],
        "moreInfo": {
          "Updated": "26 days ago",
          "Status": "Released",
          "Platforms": "HTML5",
          "Author": "PeterStubbs",
          "Genre": "Action, Platformer",
          "Tags": "2D, No AI, Retro, Singleplayer, Speedrun"
        }
      }
    },
    {
      "gameId": 4272109,
      "gameUrl": "https://s4mthewise.itch.io/cold-hard-cash",
      "overallRank": 3,
      "topCategories": [],
      "resultData": null,
      "entryData": {
        "rating_count": 81,
        "url": "/jam/bigmode-game-jam-2026/rate/4272109",
        "id": 830538,
        "created_at": "2026-02-08 06:20:50",
        "contributors": [
          {
            "url": "https://s4mthewise.itch.io",
            "name": "S4m the Wise"
          },
          {
            "url": "https://samdegroot.itch.io",
            "name": "samdegroot"
          },
          {
            "url": "https://robocop278.itch.io",
            "name": "Robocop278"
          }
        ],
        "game": {
          "title": "Cold Hard Cash",
          "cover_color": "#23244b",
          "url": "https://s4mthewise.itch.io/cold-hard-cash",
          "id": 4272109,
          "user": {
            "id": 11416236,
            "url": "https://s4mthewise.itch.io",
            "name": "S4m the Wise"
          },
          "platforms": [
            "web"
          ],
          "cover": "https://img.itch.zone/aW1nLzI1NTM1NjA0LnBuZw==/300x240%23c/ltqHoP.png",
          "short_text": "Play as a delivery driver who must deliver food during a historic snowstorm"
        },
        "coolness": 196
      },
      "details": {
        "title": "Cold Hard Cash",
        "description": "Supports controllers!\n(Average playtime: 15-30 Minutes)\nYou are a delivery driver for BigBites. The weather report has announced that one of\nthe worst winter storms in decades is going to hit the city.\nIt's advised to stay inside and not drive.\nBut... the people are hungry, and you kinda need the money...\n\nDrive fast but don't crash!\n\nEvery second counts and the people are waiting, so you will have to be quick on the road, BUT be careful not to crash too often to make sure the food makes it in one piece...\n\n\n(Made for Bigmode Jam 2026) Credits:\nRobocop278: Lead Programmer/ UI Art\nSamdegroot: Programmer/ Lead Level Designer\nR3CREAM: Lead Composer/Sound Designer\nS4m the wise: Lead 3d/2d artist                                                                                                                                                                                                                                                          ",
        "screenshots": [
          "https://img.itch.zone/aW1hZ2UvNDI3MjEwOS8yNTUzOTAwMS5wbmc=/original/HcKSjr.png",
          "https://img.itch.zone/aW1hZ2UvNDI3MjEwOS8yNTUzOTAwMi5wbmc=/original/oq0UrM.png",
          "https://img.itch.zone/aW1hZ2UvNDI3MjEwOS8yNTUzOTAwMy5wbmc=/original/kMgeU2.png"
        ],
        "moreInfo": {
          "Updated": "19 days ago",
          "Status": "Released",
          "Platforms": "HTML5",
          "Authors": "S4m the Wise, samdegroot, Robocop278",
          "Genre": "Racing, Action",
          "Made with": "Unity, Blender",
          "Tags": "Arcade, Controller, Indie, Low-poly, No AI, Singleplayer, Speedrun, Vehicles",
          "Average session": "A few minutes",
          "Languages": "English",
          "Inputs": "Keyboard, Gamepad (any)"
        }
      }
    },
    {
      "gameId": 4271732,
      "gameUrl": "https://wooglord.itch.io/one-night-window",
      "overallRank": 4,
      "topCategories": [],
      "resultData": null,
      "entryData": {
        "rating_count": 70,
        "url": "/jam/bigmode-game-jam-2026/rate/4271732",
        "id": 830308,
        "created_at": "2026-02-08 04:50:49",
        "contributors": [
          {
            "url": "https://wooglord.itch.io",
            "name": "WoogLord"
          },
          {
            "url": "https://gympiecuddles.itch.io",
            "name": "Gympiecuddles"
          },
          {
            "url": "https://duragkennyk.itch.io",
            "name": "DuragKennyK"
          },
          {
            "url": "https://nerostratos.itch.io",
            "name": "Nerostratos"
          },
          {
            "url": "https://aldine-ksp.itch.io",
            "name": "Aldine KSP"
          }
        ],
        "game": {
          "title": "ONE NIGHT WINDOW",
          "cover_color": "#202020",
          "url": "https://wooglord.itch.io/one-night-window",
          "id": 4271732,
          "user": {
            "id": 12608203,
            "url": "https://wooglord.itch.io",
            "name": "WoogLord"
          },
          "platforms": [
            "windows"
          ],
          "cover": "https://img.itch.zone/aW1nLzI1NDYyMjU4LnBuZw==/300x240%23c/8pvZnz.png",
          "short_text": "She's in town for ONE NIGHT only!  Can you seal the deal?"
        },
        "coolness": 183
      },
      "details": {
        "title": "ONE NIGHT WINDOW",
        "description": "An INFLUENCER is in town for ONE NIGHT only!  Do you have what it takes to rizz her up and get her number?  Learn your way to each girls heart through slick dialogue trees and even slicker items to upgrade your looks!-~=+=~-\nThis is a comedy based RPG making fun of dating sims and dating culture.\nMake your way through the two main girls to gain access to the exclusive VIP lounge where the INFLUENCER awaits!\nIf you can't figure it out,  talk to the GOTH GIRL and the SORORITY GIRL and they'll lead the way to those sweet digits!\nControls:\nWASD/Arrow Keys: MOVE\nZ/E/Enter: SELECT\nX: CANCEL\nESC: PAUSE\nF3 is debug if you get stuck in that screen!Unzip (the folder) and run the .exe file inside!",
        "screenshots": [
          "https://img.itch.zone/aW1hZ2UvNDI3MTczMi8yNTQ2MjM5NS5wbmc=/original/CMpjq2.png",
          "https://img.itch.zone/aW1hZ2UvNDI3MTczMi8yNTQ2MjM1Mi5wbmc=/original/EAfimt.png",
          "https://img.itch.zone/aW1hZ2UvNDI3MTczMi8yNTQ2MjM1MS5wbmc=/original/z1l6q3.png",
          "https://img.itch.zone/aW1hZ2UvNDI3MTczMi8yNTQ2MjM3NC5wbmc=/original/NO0mu%2F.png"
        ],
        "moreInfo": {
          "Status": "Released",
          "Platforms": "Windows",
          "Authors": "WoogLord, Gympiecuddles, DuragKennyK, Nerostratos, Aldine KSP",
          "Genre": "Role Playing",
          "Tags": "bigmode-2026, Comedy, Dating Sim, dialogue-trees, LÖVE, lua, Pixel Art, rizz"
        }
      }
    },
    {
      "gameId": 4248757,
      "gameUrl": "https://davinci789.itch.io/carwash-calamity",
      "overallRank": 5,
      "topCategories": [],
      "resultData": null,
      "entryData": {
        "rating_count": 134,
        "url": "/jam/bigmode-game-jam-2026/rate/4248757",
        "id": 830283,
        "created_at": "2026-02-08 04:47:07",
        "contributors": [
          {
            "url": "https://davinci789.itch.io",
            "name": "DaVinci789"
          },
          {
            "url": "https://pijinguy.itch.io",
            "name": "pijinguy"
          },
          {
            "url": "https://ginxel.itch.io",
            "name": "Virginia Leo"
          },
          {
            "url": "https://lilchokedout.itch.io",
            "name": "lilchokedout"
          }
        ],
        "game": {
          "title": "Carwash Calamity",
          "gif_cover": "https://img.itch.zone/aW1nLzI1NDYyMjc0LmdpZg==/original/FFSWcv.gif",
          "url": "https://davinci789.itch.io/carwash-calamity",
          "cover": "https://img.itch.zone/aW1nLzI1NDYyMjc0LmdpZg==/300x240%23c/eQ7u%2BO.gif",
          "short_text": "Wash cars, hose down the grime and confront the creatures clinging beneath the surface in slick, surreal battles.",
          "cover_color": "#000000",
          "id": 4248757,
          "platforms": [
            "windows",
            "web"
          ],
          "user": {
            "id": 195755,
            "url": "https://davinci789.itch.io",
            "name": "DaVinci789"
          }
        },
        "coolness": 165
      },
      "details": {
        "title": "Carwash Calamity",
        "description": "\nleft mouse click - activate hose \nmove mouse - move hose and hand\nesc - pause\n\nIn Carwash Calamity, some patches of dirt hide something alive. As you hose down filthy cars, certain stains erupt into bullet-hell encounters against the strange creatures dwelling within the grime. Dodge, survive, and clear every last speck to restore the car to a flawless, slick finish. Clean fast, every hit to you is decreased time from your timer, and customers hate waiting.DaVinci789: Programmerpijinguy: Designerlilchokedout: ArtistVirginia Leo: Composer",
        "screenshots": [
          "https://img.itch.zone/aW1hZ2UvNDI0ODc1Ny8yNTU1MTQyMi5qcGc=/original/lnTOsH.jpg",
          "https://img.itch.zone/aW1hZ2UvNDI0ODc1Ny8yNTQ2Mjc5Mi5wbmc=/original/EUgFTm.png",
          "https://img.itch.zone/aW1hZ2UvNDI0ODc1Ny8yNTQ2Mjc4OS5wbmc=/original/8oCoHt.png",
          "https://img.itch.zone/aW1hZ2UvNDI0ODc1Ny8yNTQ2Mjc5MS5wbmc=/original/ZMfrxs.png",
          "https://img.itch.zone/aW1hZ2UvNDI0ODc1Ny8yNTQ2MjgxMC5wbmc=/original/pziOs6.png",
          "https://img.itch.zone/aW1hZ2UvNDI0ODc1Ny8yNTQ2Mjc5My5wbmc=/original/lt5lt3.png"
        ],
        "moreInfo": {
          "Updated": "25 days ago",
          "Status": "Prototype",
          "Platforms": "HTML5, Windows",
          "Rating": "Rated 5.0 out of 5 stars(2 total ratings)",
          "Authors": "DaVinci789, pijinguy, Virginia Leo, lilchokedout",
          "Genre": "Action, Role Playing, Shooter, Simulation",
          "Made with": "Godot",
          "Tags": "2D, Bullet Hell"
        }
      }
    },
    {
      "gameId": 4271910,
      "gameUrl": "https://mrbuscemi.itch.io/null-signal",
      "overallRank": 6,
      "topCategories": [],
      "resultData": null,
      "entryData": {
        "url": "/jam/bigmode-game-jam-2026/rate/4271910",
        "id": 830386,
        "created_at": "2026-02-08 04:58:18",
        "rating_count": 34,
        "game": {
          "title": "Null Signal",
          "gif_cover": "https://img.itch.zone/aW1nLzI1NDg2MDQ1LmdpZg==/original/nVwWrR.gif",
          "url": "https://mrbuscemi.itch.io/null-signal",
          "cover": "https://img.itch.zone/aW1nLzI1NDg2MDQ1LmdpZg==/300x240%23c/S3GM8n.gif",
          "short_text": "3D  neon wireframe runner that reacts to music played",
          "cover_color": "#40036d",
          "id": 4271910,
          "platforms": [
            "windows"
          ],
          "user": {
            "id": 16191313,
            "url": "https://mrbuscemi.itch.io",
            "name": "MrBuscemi"
          }
        },
        "coolness": 142
      },
      "details": {
        "title": "Null Signal",
        "description": "Be a wire-frame mesh ball that endlessly runs forward in a world that reacts to the beat of any MP3 file. \nDodge everything red while trying to roll through boost rings and diamonds. Bounce pads are also there to help you dodge sections of the road. Watch out for the glitching red floor spots as they will slow you down a bit when ran over. \n_________\nThe goal so far is to just survive from falling off the sides of the map before your song ends. I had left up invisible bumpers on both sides of the playing field for quite a long distance to help stop early falling off. All of that will be improved upon soon to be better understood within the game itself. Had to take some shortcuts to get it finished in time for the game jam!\nI added a file explorer so you could test out whatever song you want. \nPlease use Alt + F4 if you want to leave mid game. I had accidentally left in code to hide the mouse cursor once you click start. Was originally to help me record the video without my cursor showing up. Oops lol. I'll have this fixed by this Friday so this whole paragraph will be gone by then. \n______________________________________________________________\nGame is not nearly done and I will be giving regular updates to the game where I will add more features to make it complete. My goal is to have it be truly endless with map changes that will drastically alter the way it looks and feels while keeping true to the wire-frame look.If you are still reading this, then know that you could just continuously hit the space bar to jump higher & higher. It was an error with how I coded the jump where as long as your momentum is going upwarrds still, you can keep jumping. I'm trying to think of a a way to implement this into the gameplay itself to be beneficial. Runs perfectly from the .exe in the zip I made. You can drop any mp3 into the music folder I included before playing to make it easier. ",
        "screenshots": [
          "https://img.itch.zone/aW1hZ2UvNDI3MTkxMC8yNTQ4MDMzNC5naWY=/original/CLWC3t.gif",
          "https://img.itch.zone/aW1hZ2UvNDI3MTkxMC8yNTQ4MDMzNi5naWY=/original/vXHK4Z.gif",
          "https://img.itch.zone/aW1hZ2UvNDI3MTkxMC8yNTQ2NDM0MS5wbmc=/original/vUK2k%2B.png",
          "https://img.itch.zone/aW1hZ2UvNDI3MTkxMC8yNTQ2NDM1Mi5wbmc=/original/s1no15.png"
        ],
        "moreInfo": {
          "Updated": "7 days ago",
          "Status": "In development",
          "Platforms": "Windows",
          "Author": "MrBuscemi",
          "Genre": "Rhythm",
          "Tags": "3D Platformer, Abstract, Endless Runner, glitch, Low-poly, Neon, Procedural Generation, Singleplayer, wireframe"
        }
      }
    },
    {
      "gameId": 4265765,
      "gameUrl": "https://dreaf.itch.io/dive-knight",
      "overallRank": 7,
      "topCategories": [],
      "resultData": null,
      "entryData": {
        "url": "/jam/bigmode-game-jam-2026/rate/4265765",
        "id": 830463,
        "created_at": "2026-02-08 05:41:35",
        "rating_count": 50,
        "game": {
          "title": "Dive Knight",
          "cover_color": "#21072f",
          "url": "https://dreaf.itch.io/dive-knight",
          "id": 4265765,
          "user": {
            "id": 16127400,
            "url": "https://dreaf.itch.io",
            "name": "Dreaf"
          },
          "platforms": [
            "web"
          ],
          "cover": "https://img.itch.zone/aW1nLzI1NDIzNjU1LnBuZw==/300x240%23c/4md1q4.png",
          "short_text": "Chain moves, combo grooves, slide smoove"
        },
        "coolness": 129
      },
      "details": {
        "title": "Dive Knight",
        "description": "Dive, spin, swirl, twirl, bounce, pounce, and dodge as you tear your way through enemies on your journey to your valiant steed. \nTry to earn the gold medal! Those are some of the fastest times we play tested, so feel free to be content with silver, like the Squire you are. (If you do manage to beat our times, post a comment! We'll add your fastest times as the coveted platinum medal.)\nWASD to move, R to reset. Walking is for losers anyway.\n\n\n\nMade for the Bigmode 2026 Game Jam!\nIf you run into any trouble figuring out what to do we attached a gameplay video where we play through the game to this page. We briefly discuss the bugs, but mostly we fuck around. \nWhen we first saw the prompt, we wondered what was truly slick in games. Is it an oil spill? A car driving game? We settled on trying to create some fluid movements and quick combos, which we feel embody the essence of slickness. Despite some bugs with the movement, we found that this ended up pretty damn slick.",
        "screenshots": [
          "https://img.itch.zone/aW1nLzI1NDIzNjU1LnBuZw==/original/wMjLgt.png"
        ],
        "moreInfo": {
          "Updated": "27 days ago",
          "Status": "Released",
          "Platforms": "HTML5",
          "Author": "Dreaf",
          "Genre": "Platformer",
          "Made with": "Unity"
        }
      }
    },
    {
      "gameId": 4271873,
      "gameUrl": "https://jamless.itch.io/a-penguin-isekai",
      "overallRank": 8,
      "topCategories": [],
      "resultData": null,
      "entryData": {
        "rating_count": 92,
        "url": "/jam/bigmode-game-jam-2026/rate/4271873",
        "id": 830245,
        "created_at": "2026-02-08 04:41:59",
        "contributors": [
          {
            "url": "https://jamless.itch.io",
            "name": "Jamless"
          },
          {
            "url": "https://emciel.itch.io",
            "name": "EMCIEL"
          },
          {
            "url": "https://xoducks.itch.io",
            "name": "xoDucks"
          },
          {
            "url": "https://drhoodie.itch.io",
            "name": "DrHoodie"
          },
          {
            "url": "https://ragingclue.itch.io",
            "name": "RagingClue"
          }
        ],
        "game": {
          "title": "A Penguin Isekai: My New Life as a Suave Penguin! Readily Accepting my Role as the Village Protector",
          "cover_color": "#18a1bb",
          "url": "https://jamless.itch.io/a-penguin-isekai",
          "id": 4271873,
          "user": {
            "id": 12555511,
            "url": "https://jamless.itch.io",
            "name": "Jamless"
          },
          "platforms": [
            "web"
          ],
          "cover": "https://img.itch.zone/aW1nLzI1NDYyMTM4LnBuZw==/300x240%23c/AT1uCB.png",
          "short_text": "A Penguin Isekai"
        },
        "coolness": 126
      },
      "details": {
        "title": "A Penguin Isekai: My New Life as a Suave Penguin! Readily Accepting my Role as the Village Protector",
        "description": "(if you die and wish to retry, the opening can be skipped with spacebar)\n\nWhen a human boy has a surprise rendezvous with Truck-kun, he wakes up to find himself in a new world inhabited by Penguins and in desperate need of a Hero! \nHe becomes Ping the Penguin, and with a surprising lack of contemplation, accepts his role as the village protector! Can Ping save the village from Leon the Leopard Seal's Evil Lava Spell and his Viking goons, using only his trusty ice cannon and slick sunnies?\nProbably!\n\nDrHoodie - Lead programming, voice of Ping and human boy\nEMCIEL - Sound Effects, music, voice of enemy ram\nJamless/Forbic - Sprite animations, title screen, programming, voice of enemy crow\nRagingClue - Cutscene artwork, tilesets, voice of mom and penguins\nxoDucks - Programming, music, voice of announcer and penguins",
        "screenshots": [
          "https://img.itch.zone/aW1hZ2UvNDI3MTg3My8yNTQ4MzI3Mi5wbmc=/original/SmO9s5.png",
          "https://img.itch.zone/aW1hZ2UvNDI3MTg3My8yNTQ4MzI3NC5wbmc=/original/3gV7%2Fz.png",
          "https://img.itch.zone/aW1hZ2UvNDI3MTg3My8yNTQ4MzI3MS5wbmc=/original/%2BToLm%2B.png",
          "https://img.itch.zone/aW1hZ2UvNDI3MTg3My8yNTQ4MzI3MC5wbmc=/original/wMPbPl.png",
          "https://img.itch.zone/aW1hZ2UvNDI3MTg3My8yNTQ4MzI3My5wbmc=/original/hKcTDz.png"
        ],
        "moreInfo": {
          "Updated": "18 days ago",
          "Status": "Released",
          "Platforms": "HTML5",
          "Authors": "Jamless, EMCIEL, xoDucks, DrHoodie, RagingClue",
          "Genre": "Action, Shooter",
          "Tags": "2D, GameMaker, No AI, Pixel Art, Singleplayer"
        }
      }
    },
    {
      "gameId": 4268262,
      "gameUrl": "https://dual-signal.itch.io/drabsville",
      "overallRank": 9,
      "topCategories": [],
      "resultData": null,
      "entryData": {
        "url": "/jam/bigmode-game-jam-2026/rate/4268262",
        "id": 829400,
        "created_at": "2026-02-07 02:00:12",
        "rating_count": 61,
        "game": {
          "title": "Drabsville",
          "url": "https://dual-signal.itch.io/drabsville",
          "id": 4268262,
          "user": {
            "id": 16191969,
            "url": "https://dual-signal.itch.io",
            "name": "Dual Signal"
          },
          "platforms": [
            "windows"
          ],
          "cover": "https://img.itch.zone/aW1nLzI1NDM5MzM2LmpwZw==/300x240%23c/DVgT9Y.jpg",
          "short_text": "Turn Drabsville into the SLICKEST town in the world!"
        },
        "coolness": 124
      },
      "details": {
        "title": "Drabsville",
        "description": "In Drabsville you play as the only SLICK member of a very Drab town. Luckily you are committed to showing them your ways and turning Drabsville into the SLICKEST town in the world.",
        "screenshots": [
          "https://img.itch.zone/aW1hZ2UvNDI2ODI2Mi8yNTUzOTg2NS5naWY=/original/wlI372.gif",
          "https://img.itch.zone/aW1hZ2UvNDI2ODI2Mi8yNTUzOTg1Ni5naWY=/original/JCJZ%2FQ.gif",
          "https://img.itch.zone/aW1hZ2UvNDI2ODI2Mi8yNTUzOTgzMC5naWY=/original/n2eajp.gif"
        ],
        "moreInfo": {
          "Status": "Released",
          "Platforms": "Windows",
          "Rating": "Rated 5.0 out of 5 stars(1 total ratings)",
          "Author": "Dual Signal",
          "Genre": "Adventure"
        }
      }
    },
    {
      "gameId": 4260190,
      "gameUrl": "https://bootable.itch.io/soul-slide",
      "overallRank": 10,
      "topCategories": [],
      "resultData": null,
      "entryData": {
        "url": "/jam/bigmode-game-jam-2026/rate/4260190",
        "id": 828729,
        "created_at": "2026-02-04 19:14:50",
        "rating_count": 81,
        "game": {
          "title": "Soul Slide",
          "url": "https://bootable.itch.io/soul-slide",
          "id": 4260190,
          "platforms": [
            "windows",
            "web"
          ],
          "cover": "https://img.itch.zone/aW1nLzI1NDAwMTA1LnBuZw==/300x240%23c/D5fQps.png",
          "user": {
            "id": 3915376,
            "url": "https://bootable.itch.io",
            "name": "Bootable"
          }
        },
        "coolness": 123
      },
      "details": {
        "title": "Soul Slide",
        "description": "Souls are trapped. Only you can free them.\nFling shapes outward across 16 directions to match three of a kind.\nMatched souls shatter and are set free. But the towers keep growing.\nMiss your matches and they'll close in on you.",
        "screenshots": [
          "https://img.itch.zone/aW1hZ2UvNDI2MDE5MC8yNTQwMDA2OC5wbmc=/original/h1aPJl.png",
          "https://img.itch.zone/aW1hZ2UvNDI2MDE5MC8yNTQwMDA4My5wbmc=/original/ZH5QCo.png"
        ],
        "moreInfo": {
          "Status": "Released",
          "Platforms": "HTML5, Windows",
          "Rating": "Rated 5.0 out of 5 stars(1 total ratings)",
          "Author": "Bootable",
          "Genre": "Puzzle"
        }
      }
    },
    {
      "gameId": 4261849,
      "gameUrl": "https://xcathedragames.itch.io/gun-knife-bomb",
      "overallRank": 11,
      "topCategories": [],
      "resultData": null,
      "entryData": {
        "url": "/jam/bigmode-game-jam-2026/rate/4261849",
        "id": 829955,
        "created_at": "2026-02-08 01:37:06",
        "rating_count": 49,
        "game": {
          "title": "Gun Knife Bomb",
          "gif_cover": "https://img.itch.zone/aW1nLzI1NDU4NDQ0LmdpZg==/original/289Pn5.gif",
          "url": "https://xcathedragames.itch.io/gun-knife-bomb",
          "cover": "https://img.itch.zone/aW1nLzI1NDU4NDQ0LmdpZg==/300x240%23c/2ggt0F.gif",
          "short_text": "A Rock-Paper-Scissors gambling game with deadly weapons.",
          "cover_color": "#000000",
          "id": 4261849,
          "platforms": [
            "windows"
          ],
          "user": {
            "id": 12653277,
            "url": "https://xcathedragames.itch.io",
            "name": "XCathedraGames"
          }
        },
        "coolness": 120
      },
      "details": {
        "title": "Gun Knife Bomb",
        "description": "Play Rock-Paper-Scissors with deadly weapons to be initiated into the elite military branch known as S.L.I.C.K.\n---How to Play---\nGun beats Knife, Knife beats Bomb, Bomb beats Gun.\nEach weapon has 3 lives. When you lose with a weapon, it loses a life.\nLose 3 lives on any of your weapons, and you lose the game. Take 3 lives on an opponent's weapon and win.\nThe scoreboard represents the lives of each weapon - the enemy's on top and yours on the bottom, in the order of gun knife bomb.\n\n Use W & S to cycle between looking at the enemy's board, the center of the table, and your board.\n\nHover over modifiers on either side of the board to see what they do.\n\nClick modifiers to use them up for the round, click the buttons to select your weapon, and click the lever to lock in your choices.\n",
        "screenshots": [
          "https://img.itch.zone/aW1hZ2UvNDI2MTg0OS8yNTUzOTYwOS5wbmc=/original/HoVWjB.png",
          "https://img.itch.zone/aW1hZ2UvNDI2MTg0OS8yNTUzOTYxNC5wbmc=/original/ZuONO1.png",
          "https://img.itch.zone/aW1hZ2UvNDI2MTg0OS8yNTUzOTYxNS5wbmc=/original/8tu228.png"
        ],
        "moreInfo": {
          "Updated": "26 days ago",
          "Status": "Released",
          "Platforms": "Windows",
          "Author": "XCathedraGames",
          "Genre": "Strategy, Puzzle, Simulation",
          "Tags": "3D, Dark, First-Person, gambling, Horror, Psychological Horror, Roguelike, Singleplayer"
        }
      }
    },
    {
      "gameId": 4262272,
      "gameUrl": "https://aimless-studios.itch.io/slick-tricks",
      "overallRank": 12,
      "topCategories": [],
      "resultData": null,
      "entryData": {
        "url": "/jam/bigmode-game-jam-2026/rate/4262272",
        "id": 829821,
        "created_at": "2026-02-07 22:59:43",
        "rating_count": 77,
        "game": {
          "title": "Slick Tricks",
          "cover_color": "#bdfffd",
          "url": "https://aimless-studios.itch.io/slick-tricks",
          "id": 4262272,
          "user": {
            "id": 7130011,
            "url": "https://aimless-studios.itch.io",
            "name": "Aimless Studios"
          },
          "platforms": [
            "web"
          ],
          "cover": "https://img.itch.zone/aW1nLzI1NDU1NzQ0LnBuZw==/300x240%23c/4LpL7i.png",
          "short_text": "Dodge and survive until the song is over"
        },
        "coolness": 110
      },
      "details": {
        "title": "Slick Tricks",
        "description": "This is an entry for the Bigmode Game Jam 2026, made by me, Aimless Studios and my lovely wife, Dilosh Designs\nWe chose two definitions for the theme \"slick\" (Source: https://dictionary.cambridge.org/dictionary/english/slick):\n\"operating or performing skilfully and effectively, without problems and without seeming to need effort\" \"smooth, wet and slippery (= difficult to move on without sliding)\"\n\nControls:\n\nA/Left: move left\nD/Right: move right\nW/Up: Jump\nS/Down: Stomp\nSpace: do a random trick\nESC: Pause\n\nFeatures:\nSlick beatsOne level with a soundtrack of 2:45Pick ups (extra score, extra HP, double jump, invincibility)Tricks (frontflip and backflip) which make you invulnerable during the performanceUpgrades (+HP, pick up spawn chance, more points per trick, more tricks per round, lower cooldown for tricks)Due to time constraits, we weren't able to polish the game enough regarding animations, sound effects and bug fixing, but we hope you like it :)\n\nDescription:\nIn Slick Tricks, you control \"Slick Rick, the Trickster\", an ice cube with one mission: survive and do as many tricks as you can\nDifferent pick ups spawn that will help you during a round\nBuy upgrades to survive even longer and make sure not to die until the end of the song (two minutes, 45 seconds)\n\nDisclaimer:\nWARNING: This game may potentially trigger seizures for people with photosensitive epilepsy.",
        "screenshots": [
          "https://img.itch.zone/aW1hZ2UvNDI2MjI3Mi8yNTQ1NTc0OC5wbmc=/original/yMGLNP.png",
          "https://img.itch.zone/aW1hZ2UvNDI2MjI3Mi8yNTQ1NTc0Ni5wbmc=/original/D%2B48uc.png",
          "https://img.itch.zone/aW1hZ2UvNDI2MjI3Mi8yNTQ1NTc0Ny5wbmc=/original/Q8NA88.png",
          "https://img.itch.zone/aW1hZ2UvNDI2MjI3Mi8yNTQ1NTc0OS5wbmc=/original/G2Z%2B5Z.png"
        ],
        "moreInfo": {
          "Updated": "18 days ago",
          "Status": "Prototype",
          "Platforms": "HTML5",
          "Author": "Aimless Studios",
          "Genre": "Rhythm, Platformer",
          "Made with": "Unity",
          "Tags": "2D, Bullet Hell, Indie, No AI, slick"
        }
      }
    },
    {
      "gameId": 4239580,
      "gameUrl": "https://henri-lamarre.itch.io/bigmodegamejam2026",
      "overallRank": 13,
      "topCategories": [],
      "resultData": null,
      "entryData": {
        "rating_count": 64,
        "url": "/jam/bigmode-game-jam-2026/rate/4239580",
        "id": 830450,
        "created_at": "2026-02-08 05:27:52",
        "contributors": [
          {
            "url": "https://henri-lamarre.itch.io",
            "name": "Henri Lamarre"
          },
          {
            "url": "https://lookinside.itch.io",
            "name": "LookInside"
          },
          {
            "url": "https://tchobis.itch.io",
            "name": "TCHOBIS"
          },
          {
            "url": "https://azaraque.itch.io",
            "name": "Azaraque"
          }
        ],
        "game": {
          "title": "Dap Mr. P",
          "cover_color": "#ace0e2",
          "url": "https://henri-lamarre.itch.io/bigmodegamejam2026",
          "id": 4239580,
          "user": {
            "id": 11393400,
            "url": "https://henri-lamarre.itch.io",
            "name": "Henri Lamarre"
          },
          "platforms": [
            "web"
          ],
          "cover": "https://img.itch.zone/aW1nLzI1NDUyMjA4LnBuZw==/300x240%23c/SbZmhp.png",
          "short_text": "You just finished the best speech of your life. People are getting in line to shake hands. Do your slickest moves!"
        },
        "coolness": 102
      },
      "details": {
        "title": "Dap Mr. P",
        "description": "",
        "screenshots": [
          "https://img.itch.zone/aW1hZ2UvNDIzOTU4MC8yNTQ3MTM4OS5wbmc=/original/eDDpez.png",
          "https://img.itch.zone/aW1hZ2UvNDIzOTU4MC8yNTQ3NzQ4NC5naWY=/original/xdEyHV.gif",
          "https://img.itch.zone/aW1hZ2UvNDIzOTU4MC8yNTQ3MTQ1My5wbmc=/original/DBkVsm.png",
          "https://img.itch.zone/aW1hZ2UvNDIzOTU4MC8yNTQ3NzQ0MS5naWY=/original/mv04k2.gif"
        ],
        "moreInfo": {
          "Updated": "29 days ago",
          "Status": "Released",
          "Platforms": "HTML5",
          "Authors": "Henri Lamarre, LookInside, TCHOBIS, Azaraque",
          "Made with": "Unity",
          "Tags": "slick",
          "Average session": "A few minutes",
          "Languages": "English",
          "Inputs": "Keyboard"
        }
      }
    },
    {
      "gameId": 4270605,
      "gameUrl": "https://jspeak.itch.io/big-punch",
      "overallRank": 14,
      "topCategories": [],
      "resultData": null,
      "entryData": {
        "url": "/jam/bigmode-game-jam-2026/rate/4270605",
        "id": 829783,
        "created_at": "2026-02-07 22:08:55",
        "rating_count": 93,
        "game": {
          "title": "BIG PUNCH",
          "cover_color": "#34314f",
          "url": "https://jspeak.itch.io/big-punch",
          "id": 4270605,
          "user": {
            "id": 9472340,
            "url": "https://jspeak.itch.io",
            "name": "jSpeak"
          },
          "platforms": [
            "web"
          ],
          "cover": "https://img.itch.zone/aW1nLzI1NDU0ODcyLnBuZw==/300x240%23c/JyhVoM.png",
          "short_text": "Kill 100 gorblins with ONE punch!"
        },
        "coolness": 100
      },
      "details": {
        "title": "BIG PUNCH",
        "description": "BIG PUNCH\nKill 100 gorblins with one punch!\nA controller is recommended for this game.\nController Controls (Xbox Layout)FunctionJoystickMovePress AAim PunchRelease APunch!YUpgrade Shop\nKeyboard ControlsFunctionWASD or Arrow KeysMovePress Space or QAim PunchRelease Space or QPunch!F Upgrade Shop\nMusic: Next to You by Joth",
        "screenshots": [
          "https://img.itch.zone/aW1hZ2UvNDI3MDYwNS8yNTQ1NTk5MS5naWY=/original/qyPMch.gif",
          "https://img.itch.zone/aW1hZ2UvNDI3MDYwNS8yNTQ1NjQ2Mi5wbmc=/original/XCOJ75.png"
        ],
        "moreInfo": {
          "Updated": "21 hours ago",
          "Status": "Released",
          "Platforms": "HTML5",
          "Author": "jSpeak",
          "Genre": "Action",
          "Made with": "Aseprite, SDL",
          "Tags": "Bullet Hell, Incremental",
          "Average session": "About a half-hour",
          "Inputs": "Keyboard, Gamepad (any)"
        }
      }
    },
    {
      "gameId": 4263388,
      "gameUrl": "https://lion-yawn.itch.io/00skatin",
      "overallRank": 15,
      "topCategories": [],
      "resultData": null,
      "entryData": {
        "rating_count": 87,
        "url": "/jam/bigmode-game-jam-2026/rate/4263388",
        "id": 830000,
        "created_at": "2026-02-08 02:29:34",
        "contributors": [
          {
            "url": "https://lion-yawn.itch.io",
            "name": "Lion Yawn"
          },
          {
            "url": "https://brainofcubes.itch.io",
            "name": "brainofcubes"
          },
          {
            "url": "https://tortugan.itch.io",
            "name": "Tortugan"
          },
          {
            "url": "https://magnaremora.itch.io",
            "name": "MagnaRemora"
          },
          {
            "url": "https://jakethekraz.itch.io",
            "name": "Jakethehumanjr"
          },
          {
            "url": "https://mathcong.itch.io",
            "name": "Mathcong"
          }
        ],
        "game": {
          "title": "Double-O Skatin': Toogan Infiltration",
          "gif_cover": "https://img.itch.zone/aW1nLzI1NDYwOTQ0LmdpZg==/original/iBL6J7.gif",
          "url": "https://lion-yawn.itch.io/00skatin",
          "cover": "https://img.itch.zone/aW1nLzI1NDYwOTQ0LmdpZg==/300x240%23c/1PKTQ%2F.gif",
          "short_text": "Roll through the city to stop a surge of mutants.",
          "cover_color": "#000000",
          "id": 4263388,
          "platforms": [
            "windows",
            "web"
          ],
          "user": {
            "id": 9258701,
            "url": "https://lion-yawn.itch.io",
            "name": "Lion Yawn"
          }
        },
        "coolness": 92
      },
      "details": {
        "title": "Double-O Skatin': Toogan Infiltration",
        "description": "WARNING: Restarting a level from the pause menu will stop the music. Restart with r or the select button to avoid this.\nControls\nSkate and dash: A and D // Left stickJump: W or Space // [A] button\nBullet time: Left click // Right stickSlam: S // Down\nCredits:\nlionyawn - Programmermathcong - Artistbrainofcubes - Artistmagnaremora - Music/SFXjakethehumanjr - Music/SFXfluppy - Voice acting",
        "screenshots": [
          "https://img.itch.zone/aW1hZ2UvNDI2MzM4OC8yNTQ2MTgxNy5naWY=/original/%2FXiSLu.gif",
          "https://img.itch.zone/aW1hZ2UvNDI2MzM4OC8yNTQ2MTgyMy5wbmc=/original/eF00X8.png",
          "https://img.itch.zone/aW1hZ2UvNDI2MzM4OC8yNTQ2MTgyNy5wbmc=/original/F6MhDj.png",
          "https://img.itch.zone/aW1hZ2UvNDI2MzM4OC8yNTQ2MTg1NC5wbmc=/original/qKBTMY.png"
        ],
        "moreInfo": {
          "Updated": "26 days ago",
          "Status": "In development",
          "Platforms": "HTML5, Windows",
          "Rating": "Rated 3.5 out of 5 stars(2 total ratings)",
          "Authors": "Lion Yawn, brainofcubes, Tortugan, MagnaRemora, Jakethehumanjr, Mathcong",
          "Genre": "Action",
          "Made with": "GameMaker",
          "Tags": "Pixel Art, Shoot 'Em Up, Side Scroller"
        }
      }
    }
  ]
}